Workbook

Sheet Evaluation
A1: Crédit | C1: Critère | D1: Phases | E1: Prérequis | F1: Nb. crédits | G1: Scénario 1 | H1: Scénario 2 | I1: Scénario 3 | K1: Description v7 | L1: Description v6 | M1: Inséré dans PROG ENV | N1: Réponse du projet / observation
A2: Man 01 | B2: Planning du projet | C2: 1-3 | D2: ESQ | E2: - | F2: 1 | G2: 1 | H2: 1 | I2: 1 | J2: Mission de base ESSOR | K2: 1. Un programme de durabilité clair est développé avant l'achèvement de la conception initiale qui définit : 1.a. Les exigences du client, par exemple les conditions environnementales internes requises 1.b. Les objectifs et les cibles de durabilité comprenant le classement BREEAM visé, les objectifs de l'entreprise, etc. 1.c. Délais et budget 1.d. Liste des personnes consultées et les rendez-vous professionnels qui peuvent être requis, par exemple acousticien qualifié, etc. 1.e. Contraintes pour le projet, par exemple techniques, juridiques, physiques, environnementales. 2. Avant la finalisation de la conception préliminaire, l'équipe projet (client, équipe de conception et entrepreneur principal (voir M1 si non encore désigné)) se réunit afin de discuter, d'identifier et de définir les rôles, les responsabilités et les contributions pour chaque phase clé du projet. Lors de la définition des responsabilités, les points suivants doivent être pris en compte : 2.a. Besoins des utilisateurs du bâtiment. 2.b. Objectifs et stratégie de conception. 2.c. Exigences et contraintes particulières liées à l'installation et à la construction. 2.d. Évaluations des risques liés à la conception et à la construction, par exemple la réglementation nationale en matière de santé et de sécurité ou les meilleures pratiques, l'évaluation des risques de légionellose. 2.e. Exigences législatives, par exemple la réglementation locale en matière de construction, les exigences relatives au patrimoine. 2.f. Objectifs de développement durable du projet. 2.g. Mesures de protection écologique (le cas échéant). 2.h. Approvisionnement et chaîne logistique : approvisionnement responsable et éthique. 2.i. Identification et mesure de la réussite du projet conformément aux objectifs du cahier des charges. 2.j Budget et expertise technique du gestionnaire ou des occupants de l'immeuble en matière de maintenance des systèmes proposés. 2.k. Maintenabilité et adaptabilité des propositions. 2.l. Exigences relatives à la production de la documentation de projet et de la documentation destinée à l'utilisateur final. 2.m. Exigences relatives à la mise en service, à la formation et au support après-vente 3.L'équipe de projet démontre comment les contributions des parties prenantes à la réalisation du projet et leurs apports au processus de conception ont influencé les éléments suivants : 3.a. Cahier des charges initial 3.b. Plan d'exécution du projet 3.c. Stratégie de communication 3.d. Conception préliminaire 3.e. Conception finale (après construction) | L2: Un programme de durabilité clair est développé avant l'achèvement de la conception initiale qui définit : a. Les exigences du client, par exemple les conditions environnementales internes requises b. Les objectifs et les cibles de durabilité comprenant le classement BREEAM visé, les objectifs de l'entreprise, etc. c. Délais et budget d. Liste des personnes consultées et les rendez-vous professionnels qui peuvent être requis, par exemple acousticien qualifié, etc. e. Contraintes pour le projet, par exemple techniques, juridiques, physiques, environnementales.
A3: Man 01 | B3: Consultation des parties prenantes (tiers) | C3: 4-6 | D3: ESQ | E3: - | F3: 1 | G3: 0 | H3: 0 | I3: 0 | K3: 4. Avant l'achèvement de la phase de conception initiale, tous les tiers concernés ont été consultés par l'équipe de conception. 5. Le projet doit démontrer de manière concise comment les contributions des parties intéressées et les résultats de la consultation ont influencé ou modifié le cahier des charges initial et la conception préliminaire ; et comment ces modifications ont été intégrées à la conception finale après la construction. 6. Avant l’achèvement de la conception détaillée (conception technique ou équivalent), les commentaires recueillis lors de la consultation ont été transmis à toutes les parties concernées et reçus par elles. | L3: Avant l'achèvement de la phase de travail de conception initiale, tous les tiers concernés ont été consultés par l'équipe de conception.
A4: Man 01 | B4: Responsable durabilité (conception) | C4: 7-9 | D4: ESQ | E4: - | F4: 1 | G4: 1 | H4: 1 | I4: 1 | J4: Option AP | K4: 7. Un responsable durabilité a été désigné pour faciliter l'établissement et la réalisation d'objectifs de performance BREEAM pour le projet. Leur implication doit intervenir dès le début du processus de conception (voir M3.2) afin de : 7.a Collaborer avec l’équipe projet, y compris le client, pour examiner les liens entre les enjeux BREEAM et les aider à optimiser la performance globale du projet au regard de BREEAM, dès leur nomination et tout au long de la phase de conception préliminaire. 7.b Suivre l’avancement par rapport aux objectifs de performance convenus à toutes les étapes suivant leur nomination, lorsque leurs décisions ont un impact critique sur la performance BREEAM. 7.c Identifier de manière proactive les risques et les opportunités liés à l’atteinte des objectifs convenus. 7.d Fournir un retour d'information approprié à l'équipe projet afin de l'aider à prendre des mesures correctives et à atteindre ses objectifs de performance convenus. 7.e Suivre et, le cas échéant, coordonner la production des preuves appropriées par l'équipe projet. 8. Les objectifs de performance BREEAM définis ont été formellement convenus entre le client et l'équipe de conception ou projet au plus tard au stade de la conception préliminaire. 9. Pour obtenir ce crédit lors de l'évaluation intermédiaire de la conception, les objectifs de performance BREEAM convenus doivent être démontrés par la conception du projet. Ceci doit être démontré par le rapport d'évaluation de l'évaluateur BREEAM à l'étape de la conception. | L4: Un responsable durabilité a été désigné pour faciliter l'établissement et la réalisation d'objectifs de performance BREEAM pour le projet.
A5: Man 01 | B5: Responsable durabilité (suivi des progrès) | C5: 10-12 | D5: APS-APD-PRO-DCE | E5: - | F5: 1 | G5: 1 | H5: 1 | I5: 1 | J5: Option AP | K5: 10. Obtenir la certification BREEAM AP – Conception préliminaire (critères 7 à 9). 11. Un professionnel BREEAM Advisory Professional (AP) a été désigné pour suivre l'avancement du projet par rapport aux objectifs de performance BREEAM convenus tout au long du processus de conception et pour rendre compte formellement de cet avancement au client et à l'équipe de conception. Il doit : 11.a Collaborer avec l'équipe projet, y compris le client, afin d'examiner les liens entre les problématiques BREEAM et de les aider à optimiser la performance globale du projet par rapport à BREEAM tout au long de la phase de conception détaillée. 11.b Suivre l'avancement du projet par rapport aux objectifs de performance convenus au titre du critère 8 à toutes les étapes où les décisions ont un impact critique sur le cahier des charges, le processus d'appel d'offres et la performance BREEAM. 11.c Identifier de manière proactive les risques et les opportunités liés à l'atteinte des objectifs convenus au titre du critère 8. 11.d Fournir un retour d'information à l'équipe projet, le cas échéant, afin de l'aider à prendre des mesures correctives et à atteindre ses objectifs de performance convenus. 11.e Suivre et, le cas échéant, coordonner la production des éléments de preuve pertinents par l'équipe projet. 12 Le professionnel accrédité BREEAM AP – Conception doit participer aux réunions clés de l’équipe projet et de conception pendant les phases de conception préliminaire, de conception développée et de conception technique. Un rapport doit être établi pendant et avant la fin de chaque phase, au minimum. | L5: Un responsable durabilité est nommé pour suivre les progrès par rapport aux objectifs de performance BREEAM convenus tout au long du processus de conception et rendre compte formellement au client des progrès de l'équipe conception.
A6: Man 02 | B6: Analyse en coût global élémentaire | C6: 1-3 | D6: ESQ | E6: - | F6: 2 | G6: 0 | H6: 2 | I6: 1 | J6: Option étude en coût global | K6: 1. Une personne compétente réalise une évaluation préliminaire et une évaluation complète des options de coût du cycle de vie (CCV) des éléments de l'actif (au moins deux) au stade de la conception préliminaire, conformément à la norme ISO 15686-5:2017. 2. Le plan CCV des éléments : 2.a. Fournit une indication des coûts de remplacement futurs sur une période d’analyse définie par le client (par exemple, 20, 30, 50 ou 60 ans). 2.b. Comprend des estimations de la durée de vie, de la maintenance et des coûts d’exploitation. 3. Démontrer, à l'aide d'exemples appropriés fournis par l'équipe de conception, comment le plan LCC élémentaire a été utilisé pour influencer la conception et la spécification des bâtiments et des systèmes afin de minimiser les coûts du cycle de vie et de maximiser la valeur critique. | L6: Un coût de cycle de vie (LCC – Life Cycle Cost) élémentaire a été réalisé à l'étape de la conception initiale, ainsi que toute évaluation d'option de conception. Selon ISO 15686-5:2008
A7: Man 02 | B7: Plan de LCC au niveau composants | C7: 4-5 | D7: PRO-DCE | E7: - | F7: 1 | G7: 0 | H7: 1 | I7: 1 | J7: Option étude en coût global | K7: 4. Une personne compétente réalise une évaluation des options d'analyse du coût du cycle de vie (ACV) au niveau des composants (au moins deux) à la fin de la phase de conception technique (équivalente à la phase 4 du processus), conformément à la norme ISO 15686-5:2017. Cette évaluation inclut les types de composants suivants (le cas échéant) : 4.a Enveloppe (par exemple, bardage, fenêtres ou toiture). 4.b Services (par exemple, source de chaleur, source de refroidissement ou systèmes de contrôle, y compris les systèmes de contrôle d'éclairage intelligents par rapport aux systèmes de contrôle standard). 4.c Finitions (par exemple, murs, sols ou plafonds). 4.d Espaces extérieurs (par exemple, aménagements paysagers alternatifs, protection des limites de propriété). 5. Démontrer, à l'aide d'exemples appropriés fournis par l'équipe de conception, comment l'évaluation des options LCC au niveau des composants a été utilisée pour influencer la conception et la spécification des bâtiments et des systèmes afin de minimiser les coûts du cycle de vie et de maximiser la valeur critique. | L7: Un plan de LCC au niveau composants a été développé avant la fin du processus du PRO, selon la norme ISO 15686-5:2008
A8: Man 02 | B8: Suivi du coût du capital | C8: 6 | D8: AOR-DOE | E8: - | F8: 1 | G8: 1 | H8: 1 | I8: 1 | J8: Communication du montant au BRE (confidentiel) | K8: 6. Indiquez le coût d’investissement du bâtiment par unité de surface intérieure brute. | L8: Indiquer au BRE le coût total de l'opération
A9: Man 03 | B9: Prérequis | C9: 1-2 | D9: Chantier | E9: Pass, Good, Very Good | F9: 0 | G9: 0 | H9: 0 | I9: 0 | J9: A être mentionné sur tous les CCTP : provenance légal du bois (bois d'œuvre également, produits temporaire de chantier) | K9: 1. Tous les produits en bois et à base de bois utilisés dans le projet sont certifiés « Bois légalement récoltés et négocié » (FSC - PEFC) 2. L’ensemble de la législation et de la réglementation nationales en matière de santé et de sécurité sur les chantiers de construction sont prises en compte et mises en œuvre à toutes les phases du projet (voir CN1 page 58) : 2.a Conception de l’ouvrage : afin de minimiser les risques pour la santé et la sécurité. 2.b Planification et organisation des travaux préalables à la construction : afin de recueillir les informations relatives à la santé et à la sécurité auprès de toutes les parties prenantes concernées. 2.c Aménagement du chantier : afin de mettre en place les dispositifs de santé et de sécurité. 2.d Construction : afin de gérer, de contrôler et de rendre compte de la santé et de la sécurité du personnel du chantier. Ces informations doivent être synthétisées dans un rapport. | L9: Tous les produits en bois et à base de bois utilisés dans le projet sont certifiés « Bois légalement récoltés et négocié » (FSC - PEFC) Le projet se conforme aux obligations réglementaires de sécurité et de santé
A10: Man 03 | B10: Gestion environnementale | C10: 3-4 | D10: Chantier | E10: - | F10: 1 | G10: 0 | H10: 0 | I10: 1 | J10: Entreprises (qui construisent) sont ISO 14001 | K10: 3. Toutes les parties intervenant sur le chantier, à quelque étape que ce soit, doivent mettre en œuvre un système de management environnemental (SME) couvrant leurs principales activités. Ce SME doit être certifié par un organisme tiers selon la norme ISO 14001, EMAS (Système européen de management environnemental et d'audit) ou une norme équivalente. 4. Toutes les parties intervenant sur le chantier, à quelque étape que ce soit (par exemple, l'entrepreneur principal ou l'entreprise de démolition) doivent mettre en œuvre sur le site les meilleures pratiques en matière de prévention de la pollution, conformément aux politiques et procédures établies. Pour démontrer leur conformité, l'équipe projet doit compléter la liste de contrôle figurant dans le tableau 11, page 56, en indiquant comment l'objectif de chaque section (par exemple, la qualité de l'air) a été atteint, même par des moyens différents de ceux suggérés. Pour l'alignement avec la taxonomie européenne, veuillez vous référer à M5. | L10: L'entrepreneur principal est certifié ISO14001 ou équivalent. Mettre en place les meilleures pratiques en termes de politiques de prévention et procédures environnementales sur site.
A11: Man 03 | B11: Conseiller BRREAM (AP) | C11: 5-7 | D11: Chantier | E11: - | F11: 1 | G11: 1 | H11: 1 | I11: 1 | J11: Option AP | K11: 5. Le client doit convenir formellement avec l'entrepreneur des objectifs de performance relatifs à la certification BREEAM qui ont été fixés pour le projet. 6. Un accréditeur BREEAM (AP) doit être impliqué dans le projet au moment opportun et au niveau approprié afin de garantir l'atteinte des objectifs de performance convenus. Plus précisément, l'accréditeur doit : 6.a. Collaborer avec l'équipe projet, y compris le client, pour l'aider à optimiser la performance par rapport aux objectifs convenus tout au long de la construction, de la réception et de la clôture du projet. Cet accompagnement comprendra la prise en compte des liens entre les critères qui doivent être respectés dans tous les domaines du projet évalués par BREEAM (par exemple, Management, Énergie, Écologie, etc.), en allant au-delà des intentions de conception chaque fois que cela est possible. 6.b. Suivre l'avancement par rapport aux objectifs de performance convenus à toutes les étapes de la construction, en accordant une attention particulière aux décisions susceptibles d'avoir un impact critique sur la performance BREEAM, et en conservant tous les documents nécessaires à l'évaluation. 6.c. Identifier de manière proactive les risques et les opportunités liés aux processus d'approvisionnement et de construction, ainsi qu'à l'atteinte des objectifs convenus au titre du critère 5. 6.d Fournir un retour d'information rapide et régulier à l'entrepreneur et à l'équipe projet afin d'aider le projet à rester sur la bonne voie pour atteindre ses objectifs et de soutenir la mise en œuvre des actions correctives nécessaires. 6.e Le cas échéant, coordonner et aider l'équipe projet à fournir à l'évaluateur les éléments de preuve nécessaires à l'obtention des crédits. 7 Pour obtenir ce crédit lors de l'évaluation finale post-construction, le rapport de l'évaluateur soumis doit démontrer qu'un professionnel accrédité BREEAM a été désigné et que les objectifs de performance convenus ont été atteints de manière probante par le projet. | L11: Un responsable durabilité est nommé pour suivre le projet pour garantir la conformité continue avec les critères pertinents de performance et de processus de durabilité, et donc les objectifs BREEAM, au cours des étapes de construction, de livraison et de clôture.
A12: Man 03 | B12: Gestion responsable de la construction | C12: 8-9 | D12: Chantier | E12: Excellent (1 crédit), Outstanding (2 crédits) | F12: 2 | G12: 1 | H12: 1 | I12: 2 | J12: Mission de base ESSOR | K12: 8. Pour les projets de petite envergure ou les maisons individuelles : 8.a L’entrepreneur doit satisfaire aux exigences des points f, h, i, j et m (tels qu’ils figurent dans le tableau 10) pour obtenir un crédit. 8.b Si l’entrepreneur satisfait aux exigences des points cochés comme « requis pour un crédit (pour les projets standard) » dans le tableau 10, le projet de petite envergure ou la maison individuelle peut obtenir deux crédits. 9. Tous les bâtiments qui ne sont pas définis comme des projets à petite échelle ou des maisons individuelles sont considérés comme des projets standards et les crédits sont attribués comme suit : 9.a Tous les éléments cochés comme « requis pour un crédit (pour les projets standards) » dans le tableau 10 doivent être remplis pour qu’un crédit soit attribué. 9.b Les projets qui remplissent le critère 9.a ainsi que six autres éléments du tableau 10 peuvent se voir attribuer un deuxième crédit. | L12: le constructeur principal s’organise d’une manière qui garantisse un accès sûr et approprié au chantier, aux alentours et sur le chantier lui-même. Il respecte les critères identifiés par thème de la checklist (1point) et 6 critères de plus (2 points)
A13: Man 03 | B13: Prérequis - Suivi des impacts chantier | C13: 10 | D13: Chantier | E13: - | F13: 0 | G13: 0 | H13: 0 | I13: 0 | K13: 10. Attribuer la responsabilité de la surveillance du site à une personne nommée. Il s’agit d’une condition préalable à l’attribution de crédits pour la surveillance du site décrits ci-dessous. La personne responsable doit avoir l’autorité et l’expérience appropriées pour accéder aux données requises. Cela peut être le BREEAM AP, lorsqu'il a été nommé. Il sera tenu de surveiller, enregistrer et communiquer les données (lorsqu’elles sont mesurées) sur la consommation d’énergie, d’eau et de transport résultant de tous les processus de construction sur site (et de fabrication dédiée hors site) tout au long du programme de construction.
A14: Man 03 | B14: Suivi des impacts chantier - eau et énergie | C14: 11-16 | D14: Chantier | E14: - | F14: 1 | G14: 1 | H14: 1 | I14: 1 | J14: Mission de base ESSOR | K14: 11. Définir, dès la phase de conception, des objectifs de consommation énergétique du chantier en kWh (et, le cas échéant, en litres de carburant utilisés) résultant de l'utilisation des engins de chantier, des équipements (mobiles et fixes) et des installations de chantier. 12. Suivre et enregistrer les données relatives à la consommation énergétique décrite au critère 11 et démontrer que les objectifs de consommation ont été atteints. 13. Rendre compte des émissions totales de dioxyde de carbone (kgCO₂e) et de la consommation énergétique (électricité en kWh et litres de carburant) résultant du processus de construction. 14. Définir, dès la phase de conception, des objectifs de consommation d'eau potable (m³) liés à l'utilisation des engins de chantier, des équipements (mobiles et fixes) et des installations de chantier. 15. Suivre et enregistrer les données relatives à la consommation d'eau potable décrite au critère 14 et démontrer que les objectifs de consommation ont été atteints. 16. Utiliser les données collectées pour établir le calcul de la consommation nette totale d'eau résultant du processus de construction (m³), c'est-à-dire la consommation moins l'utilisation d'eau recyclée. | L14: Une personne sur site est en charge du suivi de la consommation d'énergie, des émissions de CO2 qui en résultent et de la consommation d'eau potable pour le chantier.
A15: Man 03 | B15: Suivi des impacts chantier - transport des matériaux de construction et des déchets | C15: 17-18 | D15: Chantier | E15: - | F15: 1 | G15: 1 | H15: 1 | I15: 1 | J15: Suivre les entrées de livraison | K15: 17. Définir des objectifs dès la phase de conception et surveiller et enregistrer les données relatives aux mouvements de transport et autres impacts résultant de la livraison de la majorité des matériaux de construction sur le chantier et de l'évacuation des déchets de construction (voir M4). Ce suivi doit au minimum couvrir : 17.a Le transport des matériaux du point d'approvisionnement au chantier, y compris le transport, le stockage intermédiaire et la distribution. 17.b Le périmètre de ce suivi doit couvrir au minimum les matériaux utilisés pour les éléments suivants : 17.b.i La superstructure, telle qu'indiquée dans le tableau 73 du document 03. 17.b.ii Les finitions intérieures, telles qu'indiquées dans le tableau 74 du document 03. 17.b.iii Les infrastructures et les aménagements extérieurs, tels qu'indiqués dans le tableau 75 du document 03. 17.b.iv Services essentiels du bâtiment, tels qu'ils figurent au tableau 76 du document 03. 17.c Transport des déchets de construction depuis le point de départ du chantier jusqu'au site de traitement ou au centre de valorisation. Le suivi doit couvrir les catégories de déchets de construction décrites dans le plan de gestion des déchets du projet. 18. À partir des données collectées, établir un rapport distinct pour les matériaux et les déchets, indiquant les émissions totales de dioxyde de carbone liées au transport (kgCO₂e), ainsi que la distance totale parcourue (km) et la quantité de carburant utilisée (litres). | L15: Suivre et enregistrer les données sur les mouvements de transport et les impacts résultant de la livraison de la majorité des matériaux des travaux de rénovation ou d'aménagement vers le chantier et des déchets.
A16: Man 03X | B16: Niveau exemplaire | C16: 19 | D16: Chantier | E16: - | F16: 1 | G16: 0 | H16: 0 | I16: 1 | K16: 19. Atteindre l'ensemble des items de la table 10. | L16: Atteindre l'ensemble des items de la table 10.
A17: Man 04 | B17: Calendrier et responsabilité | C17: 1-5 | D17: PRO-DCE-VISA-DET-AOR-DOE | E17: Very Good, Excellent, Outstanding | F17: 0 | G17: 0 | I17: 1 | J17: A faire en APD PRO | K17: 1. Élaborer un calendrier de mise en service et d'essais. Ce calendrier doit définir et inclure un échéancier approprié pour la mise en service et la remise en service de tous les systèmes techniques et de contrôle du bâtiment, complexes et non complexes, et pour les essais et l'inspection de l'enveloppe du bâtiment. 2. Le calendrier doit préciser les normes applicables auxquelles toutes les activités de mise en service seront conformes. Il s'agira notamment des codes de bonnes pratiques nationaux en matière de mise en service ou d'autres normes pertinentes, le cas échéant. Voir CN1. Tout équipement lié aux procédés ou à la fabrication, spécifié dans le cadre du projet, peut être exclu de l'évaluation, sauf s'il fait partie intégrante des services CVC du bâtiment, comme certains systèmes de récupération de chaleur. 3. Lorsqu'un système de gestion technique du bâtiment (GTB) est spécifié : 3.a. Procéder à la mise en service des systèmes d'air et d'eau une fois que tous les dispositifs de contrôle sont installés, câblés et fonctionnels. 3.b. Inclure les mesures physiques des températures ambiantes, des températures hors serpentin et autres paramètres clés, le cas échéant, dans les résultats de la mise en service. 3.c. L'installation GTB ou de contrôle doit fonctionner en mode automatique avec des conditions internes satisfaisantes avant la réception. 3.d. Tous les schémas et graphiques de la GTB (le cas échéant) sont entièrement installés et fonctionnels pour l'interface utilisateur avant la réception. 3.e. Former pleinement l'occupant ou l'équipe technique à l'utilisation du système. 4. Désigner un membre approprié de l'équipe projet pour surveiller et programmer la pré-mise en service, la mise en service et les essais. Le cas échéant, inclure les activités de remise en service pour le compte du client. 5. L’entrepreneur principal intègre le programme de mise en service et d’essais, les responsabilités et les critères dans son budget et le programme principal des travaux. Le programme doit prévoir le temps nécessaire à la réalisation de toutes les activités de mise en service. et d’essais avant la réception. | L17: Planifier le commissionnement, nommer un responsable au sein de l'équipe. Inclure le commissionnement au planning.
A18: Man 04 | B18: Commissionnement - mise en route | C18: 6-7 | D18: PRO-DCE-VISA-DET-AOR-DOE | E18: - | F18: 0 | G18: 0 | H18: 0 | I18: 1 | J18: Faire intervenir un spécialiste du commissionnement | K18: 6. Respecter le calendrier et les responsabilités (critères 1 à 5). 7. Pendant la phase de conception, le client ou l'entrepreneur principal désigne un membre approprié de l'équipe projet (voir critère 4), à condition qu'il ne participe pas aux travaux d'installation générale des systèmes techniques du bâtiment, avec les responsabilités suivantes : 7.a. Réaliser des revues de conception et fournir des conseils visant à optimiser le processus de mise en service. 7.b. Apporter son expertise en matière de gestion de la mise en service à la planification des travaux et pendant les phases d'installation. 7.c. Gérer la mise en service, les essais de performance et les phases de réception ou de post-réception. Pour les bâtiments dotés de systèmes et de services techniques complexes, ce rôle doit être assuré par un responsable de la mise en service spécialisé. | L18: Un spécialiste du commissionnement est désigné avant la fin de l'APD et est présent jusqu'à la livraison.
A19: Man 04 | B19: Essais et inspection de l'enveloppe | C19: 8-10 | D19: 4-5-6 | E19: - | F19: 1 | G19: 0 | H19: 0 | I19: 1 | J19: Faire intervenir un spécialiste de l'enveloppe | K19: 8. Respecter le calendrier et les responsabilités (critères 1 à 5). 9. Réaliser les essais et inspections post-construction afin de garantir l'intégrité de l'enveloppe du bâtiment, notamment la continuité de l'isolation, l'absence de ponts thermiques et de fuites d'air (par le biais de tests d'étanchéité à l'air et d'une inspection thermographique) (voir M1). Un professionnel qualifié effectue l'inspection et les essais conformément à la norme appropriée (voir M1.5). Pour la conformité à la taxonomie européenne, veuillez consulter M1.6. 10. Remédier à tout défaut identifié lors des essais et inspections post-construction avant la réception du bâtiment et la clôture du chantier. Tous les travaux de réparation doivent respecter les caractéristiques de performance requises pour le bâtiment ou l'élément, telles que définies lors de la conception (voir M1.4). | L19: l'intégrité des matériaux du bâtiment, y compris la continuité de l'isolation, l'évitement des ponts thermiques et les fuites d'air est assurée par la réalisation des essais et de l'inspection postconstruction. Les défaut identifiés sont corrigés avant la livraison du bâtiment
A20: Man 04 | B20: Livraison | C20: 11-12 | D20: AOR-DOE | E20: Very Good, Excellent, Outstanding | F20: 0 | G20: 0 | H20: 0 | I20: 1 | K20: 11. Avant la remise des clés, élaborer deux guides d'utilisation (voir M2) pour le bâtiment ou le logement, destinés aux utilisateurs suivants : 11.a Un guide d'utilisation non technique à distribuer aux occupants du bâtiment. 11.b Un guide d'utilisation technique destiné aux gestionnaires des installations (peut ne pas s'appliquer aux évaluations résidentielles sans parties partagées ou espaces communs gérés). Une version préliminaire est élaborée et discutée au préalable avec les utilisateurs (lorsque les occupants du bâtiment sont connus) afin de s'assurer que le guide est le plus approprié et utile possible. 12. Préparer deux programmes de formation (voir M3) adaptés aux dates de remise des clés et d'occupation prévues pour les utilisateurs suivants : 12.a Programme de formation non technique pour les occupants du bâtiment. 12.b Programme de formation technique pour les gestionnaires des installations. | L20: Un guide de l'utilisateur du bâtiment est rédigé avant la livraison pour distribution aux occupants du bâtiment et aux gestionnaires des locaux. Une formation est planifiée pour les occupants du bâtiment ou les gestionnaires des locaux.
A21: Man 05 | B21: Services de suivi après-vente | C21: 1-2 | D21: 6-7 | E21: - | F21: 0 | G21: 0 | H21: 0 | I21: 1 | K21: 1. Fournir un soutien après-vente aux occupants du bâtiment grâce à la mise en place d'une infrastructure et de ressources opérationnelles. Ceci comprend au minimum : 1.a Une réunion entre l'équipe ou la personne chargée du soutien après-vente et l'occupant ou l'équipe de gestion du bâtiment (avant l'emménagement initial, ou dès que possible par la suite) afin de : 1.a.i Présenter le soutien après-vente disponible, y compris le contenu du guide d'utilisation du bâtiment (le cas échéant) et le programme de formation. 1.a.ii Présenter les informations clés concernant les caractéristiques du bâtiment, notamment son objectif de conception et son utilisation, afin de garantir un fonctionnement aussi efficace et performant que possible. 1.b Formation à la gestion des installations sur site, comprenant : 1.b.i Visite guidée du bâtiment. 1.b.ii Présentation et familiarisation avec les systèmes du bâtiment, leurs commandes et leur utilisation conformément aux spécifications de conception et aux exigences opérationnelles. 1.c Assistance initiale pendant au moins le premier mois d'occupation du bâtiment, par exemple une présence hebdomadaire sur site, afin d'accompagner les utilisateurs et la direction du bâtiment (la fréquence dépendra de la complexité du bâtiment et de son exploitation). 1.d Assistance à plus long terme pour les occupants pendant au moins les 12 premiers mois suivant l'emménagement, par exemple une assistance téléphonique, une personne référente ou tout autre système approprié pour accompagner les utilisateurs et la direction du bâtiment. 2 Mise en place de l'infrastructure et des ressources opérationnelles nécessaires à la collecte et au suivi des données de consommation d'énergie et d'eau pendant au moins 12 mois après l'occupation significative du bâtiment. Cela facilite l’analyse des écarts entre les performances réelles et prévues, en vue d’ajuster les systèmes et les comportements des utilisateurs en conséquence (voir M1). | L21: Il y a (ou il y aura) une infrastructure de fonctionnement et des ressources en place pour fournir des services de suivi aux occupants du bâtiment ET pour coordonner la collecte et le suivi des données de consommation d'énergie et d'eau pour un minimum de 12 mois.
A22: Man 05 | B22: Commissionnement - première année | C22: 3 | D22: 6-7 | E22: Excellent, Outstanding | F22: 0 | G22: 0 | H22: 0 | I22: 1 | J22: Faire intervenir un spécialiste du commissionnement | K22: 3. Réaliser les activités de mise en service suivantes sur une période minimale de 12 mois, une fois le bâtiment occupé de manière significative : 3.a Systèmes complexes : Le responsable de la mise en service spécialisé devra : 3.a.i Identifier les modifications apportées par le propriétaire ou l’exploitant susceptibles d’avoir affecté ou amélioré les performances. 3.a.ii Tester tous les équipements techniques du bâtiment en conditions de charge maximale et partielle (voir CN1). 3.a.iii Le cas échéant, effectuer des tests pendant les périodes d’occupation extrême (forte ou faible). 3.a.iv Interroger les occupants du bâtiment (lorsqu’ils sont concernés par les équipements techniques complexes) afin d’identifier les problèmes ou les préoccupations concernant l’efficacité des systèmes. 3.a.v Comparer les performances énergétiques mesurées par sous-comptage aux performances énergétiques prévues. 3.a.vi Identifier les inefficacités et les points à améliorer. 3.a.vii Remettre en service les systèmes (après les travaux nécessaires pour répondre aux nouvelles charges) et intégrer les modifications apportées aux procédures d’exploitation dans les manuels d’exploitation et de maintenance. 3.b Systèmes simples : Le consultant externe, l’équipe de maintenance ou le gestionnaire des installations devra : 3.b.i Examiner le confort thermique, la ventilation et l’éclairage à trois, six et neuf mois après la mise en service, par des mesures ou grâce aux retours des occupants. 3.b.ii Identifier les défaillances et les points à améliorer. 3.b.iii Remettre en service les systèmes et intégrer les modifications pertinentes des procédures d’exploitation dans les manuels d’exploitation et de maintenance. | L22: Les activités de commissionnement saisonnier sont réalisées sur une période minimale de 12 mois, une fois que le bâtiment est occupé de manière importante.
A23: Man 05 | B23: Évaluation post-occupation | C23: 4-7 | D23: 7 | E23: - | F23: 0 | G23: 0 | H23: 0 | I23: 0 | J23: Coût d'une telle étude ? | K23: 4. Le client ou l'occupant du bâtiment s'engage à réaliser une évaluation post-occupation (EPO) un an après l'occupation substantielle du bâtiment. Cette évaluation permet de recueillir un retour d'information complet sur les performances en situation réelle (voir critère 5.b.v) et d'identifier les écarts entre les intentions de conception et les performances réelles. L'objectif est de mettre en évidence les améliorations ou interventions nécessaires et d'éclairer les processus opérationnels. 5. L'EPO est réalisée par un organisme indépendant et porte sur : 5.a. Un examen des intentions de conception et du processus de construction (examen des processus de conception, d'approvisionnement, de construction et de réception). 5.b. Un retour d'information d'un large éventail d'utilisateurs du bâtiment, y compris les gestionnaires d'installations, sur la conception et les conditions environnementales du bâtiment : 5.b.i Conditions environnementales intérieures (lumière, bruit, température, qualité de l'air). 5.b.ii Contrôle, exploitation et maintenance. 5.b.iii Installations et commodités. 5.b.iv Accès et agencement. 5.b.v Consommation d'énergie et d'eau (voir critère 2 et M1). 5.b.vi Autres points pertinents, le cas échéant. 6. L'organisme indépendant remet au client et aux occupants du bâtiment un rapport d'analyse des enseignements tirés. 7. Le client ou l'occupant du bâtiment s'engage à financer l'évaluation post-interventionnelle (EPI) à l'avance. Ceci implique la désignation d'un organisme indépendant pour réaliser l'EPI conformément au critère 5. | L23: Le client ou l'occupant du bâtiment prend l'engagement de procéder à un exercice d'évaluation post occupation (EPO) un an après l'occupation initiale du bâtiment.
A24: Man 05X | B24: Planning de transition zéro carbone | C24: 8 | D24: 7 | E24: - | F24: 0 | G24: 0 | H24: 0 | I24: 1 | J24: à chiffrer | K24: 8 Lorsque les objectifs de zéro émission nette de carbone ne sont pas atteints pour les performances opérationnelles et que des combustibles fossiles sont utilisés sur site, une personne compétente élabore un plan de transition zéro carbone démontrant comment l'actif atteindra la neutralité carbone en exploitation d'ici 2050 au plus tard (voir M2). | L24: Créer une feuille de route chiffrée (technique et financière) pour supprimer toute combustion fossile et atteindre le Net Zéro d'ici 2050 au plus tard (alignement sur l'engagement COP21), avec un suivi annuel des indicateurs.
A25: Hea 01 | B25: Prérequis | C25: 1 | E25: Outstanding | F25: 0 | G25: 0 | H25: 0 | I25: 0 | K25: 1. Atteindre l'une des options suivantes : 1a : Au moins 95 % des zones concernées doivent avoir des fenêtres (verticales ou inclinées) représentant au moins 20 % de la surface de la paroi environnante. 1b : Au moins 80 % des zones concernées doivent avoir une surface vitrée équivalente à au moins 7 % de la surface au sol. | L25: Option A : Au moins 95 % des zones concernées doivent avoir des fenêtres (verticales ou inclinées) représentant au moins 20 % de la surface de la paroi environnante. Option B : Au moins 80 % des zones concernées doivent avoir une surface vitrée équivalente à au moins 7 % de la surface au sol.
A26: Hea 01 | B26: Contrôle de l'éblouissement | C26: 2-4 | D26: PC-PRO-DCE | E26: - | F26: 0 | G26: 0 | H26: 0 | I26: 1 | J26: Peu de zones à risque, étude rapide ? Petite étude à faire | K26: 2. Identifier les zones à risque d'éblouissement à l'aide d'une évaluation des risques d'éblouissement. Cette évaluation justifie également les zones jugées non exposées à un risque d'éblouissement. 3. Lorsqu'un risque a été identifié dans une zone concernée du bâtiment, une stratégie de contrôle de l'éblouissement est mise en œuvre afin d'éliminer tout risque d'éblouissement (voir M2). 4. La stratégie de contrôle de l'éblouissement n'augmente pas la consommation d'énergie pour l'éclairage. Ceci est réalisé en : 4.a. Optimisant les niveaux de lumière naturelle par tous les temps (nuageux ou ensoleillé). 4.b. S'assurant que l'utilisation ou l'emplacement des protections solaires ne perturbe pas le fonctionnement des systèmes de contrôle de l'éclairage. | L26: Identifier les zones à risque via un diagnostic spécifique. Mettre en place des solutions pour éliminer l'éblouissement dans les zones à risque. Efficacité énergétique : La stratégie ne doit pas augmenter la consommation d'éclairage artificiel. Pour cela, il faut : Maximiser l'apport de lumière quel que soit le temps (nuageux ou ensoleillé). S'assurer que les protections solaires ne perturbent pas les systèmes de gestion automatique de l'éclairage.
A27: Hea 01 | B27: Eclairement naturel | C27: 5 | D27: ESQ-APS-APD | E27: - | F27: 1 | G27: 0 | H27: 1 | I27: 0 | J27: Etude ALJ à faire (points obtenus sur Fenouillet) | K27: 5. Les critères d’éclairage naturel ont été respectés selon l’une des options décrites dans le tableau 13, page 85 (voir M3.2) : 5.a Les zones concernées du bâtiment respectent les critères d’éclairement naturel moyen et minimal des bonnes pratiques, tels que décrits dans le tableau 13, page 85. OU 5.b Les zones concernées du bâtiment respectent tout niveau de recommandation selon les critères d’éclairement naturel de la norme EN 17037:2018+A1:2021. OU 5.c Les zones concernées du bâtiment atteignent au moins le niveau d’éclairement naturel « nominalement accepté » selon la norme IES LM-83-23. | L27: Montrer un niveau d'éclairement naturel suffisant (respect des seuils de luminance, ou d'autonomie en lumière du jour). Table 13 ou EN 17037:2018+A1:2021 ou ES LM-83-23
A28: Hea 01 | B28: Ensoleillement direct sur fenêtres (Résidentiel, santé, séjours longue durée) | C28: 6-7 | D28: ESQ-APS-APD | E28: - | F28: 0 | G28: 0 | H28: 0 | I28: 0 | J28: en résidentiel uniquement | K28: 6. Obtenir au moins un point pour « Éclairage naturel » (critère 5). 7. Toutes les unités concernées doivent comporter au moins une zone recevant au moins 3 heures d'ensoleillement direct par fenêtre le jour de l'équinoxe (21 mars ou 21 septembre, représentant les conditions annuelles moyennes), par ciel dégagé (voir M4). | L28: Toutes les unités concernées doivent posséder au moins une pièce recevant au moins 3 heures de soleil direct par les fenêtres le jour de l'équinoxe (21 mars ou 21 septembre).
A29: Hea 01 | B29: Vue sur l'extérieur | C29: 8-9 | D29: APS-APD-PRO-DCE | E29: - | F29: 1 | G29: 1 | H29: 1 | I29: 0 | J29: A vérifier sur plan mais obtenu sur Fenouillet | K29: 8. Option A (Distance à la fenêtre) : 95 % de la surface au sol dans 95 % des espaces doivent être à une distance d'une fenêtre permettant une vue adéquate. La taille de la fenêtre requise augmente avec la distance : < 8 m : Fenêtre ≥ 20 % de la paroi ; 8 à 11 m : Fenêtre ≥ 25 % de la paroi ; 11 à 14 m : Fenêtre ≥ 30 % de la paroi ; > 14 m : Fenêtre ≥ 35 % de la paroi. OU 9. Option B (Qualité visuelle) : 75 % de la surface au sol dans 95 % des espaces doivent offrir : Un angle de vue horizontal ≥ 28°. Une vue sur le "paysage" ainsi qu'au moins le ciel ou le sol. | L29: Option A (Distance à la fenêtre) : 95 % de la surface au sol dans 95 % des espaces doivent être à une distance d'une fenêtre permettant une vue adéquate. La taille de la fenêtre requise augmente avec la distance : < 8 m : Fenêtre ≥ 20 % de la paroi ; 8 à 11 m : Fenêtre ≥ 25 % de la paroi ; 11 à 14 m : Fenêtre ≥ 30 % de la paroi ; > 14 m : Fenêtre ≥ 35 % de la paroi. Option B (Qualité visuelle) : 75 % de la surface au sol dans 95 % des espaces doivent offrir : Un angle de vue horizontal ≥ 28°. Une vue sur le "paysage" ainsi qu'au moins le ciel ou le sol.
A30: Hea 01X | B30: Evaluation de l'éblouissement en lumière naturelle | C30: 10-11 | D30: APS-APD-PRO-DCE | E30: - | F30: 0 | G30: 0 | H30: 0 | I30: 1 | J30: Etude spécifique | K30: 10. Obtenir le crédit pour « Contrôle de l’éblouissement » (critères 2 à 4) 11. Une évaluation a été réalisée pour démontrer la conformité à l'une des exigences suivantes et à la méthode M6 : DGP (Probabilité d'Éblouissement) : Ne doit pas dépasser 0,40 pendant plus de 5 % des heures d'exploitation annuelles à tous les postes de travail. ASE (Exposition Solaire Annuelle) : Pas plus de 10 % de l'espace occupé ne doit recevoir un éclairement de 1 000 lux ou plus pendant plus de 250 heures par an. | L30: Validation du crédit sur le contrôle de l'éblouissement et restpect d'un des critères suivants : DGP (Probabilité d'Éblouissement) : Ne doit pas dépasser 0,40 pendant plus de 5 % des heures d'exploitation annuelles à tous les postes de travail. ASE (Exposition Solaire Annuelle) : Pas plus de 10 % de l'espace occupé ne doit recevoir un éclairement de 1 000 lux ou plus pendant plus de 250 heures par an.
A31: Hea 01X | B31: Eclairement naturel exemplaire | C31: 12 | D31: APS-APD-PRO-DCE | E31: - | F31: 1 | G31: 0 | H31: 0 | I31: 0 | J31: Non visé | K31: 12. Les critères d’éclairage naturel ont été respectés selon l’une des options suivantes : 12.a Les zones concernées du bâtiment satisfont aux critères exemplaires d’éclairement naturel ponctuel moyen et minimal, tels que définis dans le tableau 14, page 87. OU 12.b Les zones concernées du bâtiment satisfont à la note la plus élevée de la norme EN 17037:2018+A1:2021 OU de la norme IES LM-83-23 et aux critères pertinents du tableau 14, page 87. | L31: Atteinte du seuil exemplaire pour l'éclairement en lumière naturelle.
A32: Hea 02 | B32: Prérequis | C32: 1 | D32: APS-APD-PRO-DCE | E32: - | F32: 0 | G32: 0 | H32: 0 | I32: 0 | J32: Facile à respecter ? Oui marquage CE | K32: 1. Tout éclairage doit être conçu pour minimiser le papillotement (flicker) et les effets stroboscopiques (voir M1), y compris sur toute sa plage de gradation et de réglage des couleurs, le cas échéant. Ceci s'applique à tout éclairage intérieur et extérieur. EU Directive 2009/125/EC | L32: Toute l'installation d'éclairage doit être conçue pour minimiser le papillotement (flicker) et les effets stroboscopiques. EU Directive 2009/125/EC
A33: Hea 02 | B33: Qualité d'éclairage interne et externe | C33: 2-4 | D33: ESQ-VISA-DET | E33: - | F33: 1 | G33: 1 | H33: 1 | I33: 1 | J33: Conformité au normes en vigueur sur l'éclairage extérieur EN 13201 series (parts 1 to 5)(8), (9), (10), (11), (12) and EN 12464-2:2024 | K33: 2. L'éclairage intérieur de toutes les zones concernées du bâtiment est conçu pour être conforme à toutes les recommandations applicables de la norme EN 12464-1:2021(7) ou à une norme nationale alternative approuvée. L'éclairage intérieur doit être adapté aux tâches effectuées, en tenant compte de la concentration et du confort des utilisateurs. Ceci peut être démontré par une stratégie de conception d'éclairage fournissant des paramètres d'éclairage conformes aux guides de bonnes pratiques nationaux (voir CN2 page 99). Les critères de conformité doivent inclure, selon le cas : 2.a Niveaux et uniformité d'éclairement 2.b Limites d'éblouissement 2.c Apparence des couleurs (lorsqu'il existe des recommandations standard) 2.d Rendu des couleurs 3. Dans les zones où des écrans d'ordinateur sont régulièrement utilisés, il est impératif de confirmer que l'éclairage a été conçu pour limiter les risques d'éblouissement conformément à une limite d'éblouissement numérique spécifiée dans les guides de bonnes pratiques nationaux. Ces critères doivent inclure : 3.a Limites de luminance des luminaires pour éviter les reflets sur les écrans. Les données des fabricants de luminaires doivent être consultées pour confirmer ce point. 3.b Pour l'éclairage indirect, les recommandations se réfèrent à la luminance du plafond éclairé et non à celle du luminaire ; un calcul effectué par l'équipe de conception est généralement nécessaire pour le démontrer. 3.c Recommandations pour l'éclairage direct, l'éclairement du plafond et l'éclairement moyen des murs. 4. Tout l'éclairage extérieur situé dans la zone de construction est spécifié conformément à la série EN 13201 (parties 1 à 5) et à la norme EN 12464-2:2024. L'éclairage extérieur doit permettre aux utilisateurs d'effectuer des tâches visuelles en extérieur de manière efficace et précise, notamment la nuit. Ceci peut être démontré par une stratégie de conception d'éclairage fournissant des paramètres d'éclairage conformes aux guides nationaux de bonnes pratiques en matière d'éclairage (voir CN2 page 99). Les critères de conformité doivent inclure, le cas échéant pour chaque type d'application : 4.a Niveaux et uniformité de l'éclairement/luminance 4.b Limites d'éblouissement 4.c Rendu des couleurs | L33: L'éclairement, la température de couleur, l'IRC doivent être en conformité avec la norme (EN 12464-1).
A34: Hea 02 | B34: Zonage et commande de l'éclairage | C34: 5-8 | D34: APS-APD-PRO-DCE | E34: - | F34: 0 | G34: 0 | H34: 0 | I34: 1 | K34: 5. L'éclairage intérieur est zoné afin de permettre aux occupants de le contrôler conformément aux critères ci-dessous pour les zones concernées présentes dans le bâtiment, le cas échéant : 5.a Les postes de travail adjacents aux fenêtres ou aux atriums et les autres zones du bâtiment sont zonés et contrôlés séparément. 5.b Dans les bureaux où la disposition du mobilier est connue : zones de quatre postes de travail maximum. 5.c Salles de séminaire et de conférence : zonées pour les zones de présentation et le public. 5.d Espaces de bibliothèque : zonage séparé pour les rayonnages, les zones de lecture et les comptoirs. 5.e Espace d'enseignement ou de démonstration. 5.f Tableau blanc ou écran d'affichage. 5.g Auditoriums : zonage pour les zones de sièges, les zones de circulation et la zone du pupitre. 5.h Espaces restauration, restaurant, café : séparation des zones de service et des espaces de restauration 5.i Commerce de détail : séparation des zones d’exposition et des comptoirs 5.j Espaces bar : séparation des zones bar et des espaces de restauration 5.k Salles de jour, salles d’attente : séparation des zones de détente et d’activités, et des espaces de circulation avec commandes accessibles au personnel 5.l Chambres d’hôtel : séparation du couloir, de la salle de bain, du bureau et de l’espace nuit (le cas échéant). 6. Les zones utilisées pour l'enseignement, les séminaires ou les conférences sont dotées de commandes d'éclairage spécifiques, adaptées à la taille et à l'usage de l'espace. Cependant, un auditorium ou un amphithéâtre classique, avec des gradins et un pupitre/une zone de démonstration/de spectacle, est généralement équipé des commandes d'éclairage suivantes : 6.a Éclairage normal complet (pour permettre les entrées et sorties, le nettoyage, etc.) 6.b Éclairage de la zone de démonstration éteint et éclairage de la zone du public réduit (pour la projection de diapositives, tout en laissant suffisamment de lumière pour que le public puisse prendre des notes) 6.c Éclairage entièrement éteint (pour la projection de diapositives monochromes ou couleur, et pour les démonstrations visuelles ou les spectacles) 6.d Éclairage localisé séparé pour le pupitre. 7. Lorsque des commandes d'éclairage automatiques sont utilisées pour des raisons d'efficacité énergétique, une commande manuelle doit être prévue. 8. De plus, les critères relatifs au type de bâtiment figurant dans le tableau 15 ci-dessous (le cas échéant) | L34: Le zonage doit respecter 1 commande pour 4 personnes max en bureaux, le contrôle doit être laissé aux occupant
A35: Hea 02X | B35: Niveau exemplaire - contrôle de l'éclairage | C35: 9-10 | D35: PRO-DCE-AOR-DOE | E35: - | F35: 0 | G35: 0 | H35: 0 | I35: 0 | K35: 9. Dans chaque zone de contrôle d'un espace occupé, l'éclairage peut être atténué manuellement par les occupants jusqu'à 20 % maximum de son flux lumineux maximal, à l'aide d'interfaces de commande d'éclairage placées à des endroits accessibles. 10. Dans chaque zone de contrôle d'un espace occupé, la couleur de l'éclairage peut être ajustée sur une plage de température de couleur corrélée, de 2 700 K ou moins à 4 000 K ou plus. Des commandes automatiques limitent la température de couleur corrélée à 2 700 K ou moins l'après-midi et le soir. | L35: L'éclairage doit pouvoir être contrôlé graduellement jusqu'à moins de 20% de sa puissance maximale. La température de couleur doit pouvoir varier de 2 700k ou moins à 4 000 k ou plus.
A36: Hea 03 | B36: Effets non visuels de la lumière | C36: 1-4 | E36: - | F36: 0 | G36: 0 | H36: 0 | I36: 0 | J36: Pas de points sur l'éclairage naturel | K36: 1. Obtenir au moins un crédit pour « Éclairage naturel » dans Hea 01 Lumière naturelle. 2. Toutes les zones concernées doivent satisfaire à l'une des conditions suivantes, selon le cas : 2.a Lorsque les positions des occupants sont connues et fixes (voir M1.1) : Toutes les positions dans toutes les zones concernées du bâtiment reçoivent un éclairement vertical d'au moins 250 lux EDI mélanopiques au niveau des yeux des occupants pendant au moins quatre heures en journée (à partir de midi au plus tard). 2.b Lorsque les positions des occupants sont inconnues ou variables (voir M1.2) : L'éclairement cylindrique à hauteur des yeux dans chaque zone concernée du bâtiment correspond à au moins 250 lux EDI mélanopiques pendant au moins quatre heures en journée (à partir de midi au plus tard). 3. Des systèmes d'éclairage électrique et des commandes permettent d'ajuster le flux et le spectre de la lumière émise au fil du temps (réglage de la couleur) afin de réduire l'EDI mélanopique au niveau des yeux des occupants l'après-midi et le soir, selon le type d'application. 4. Dans les zones résidentielles d'un bâtiment, des systèmes et des commandes garantissent un EDI mélanopique inférieur ou égal à 10 lux pendant les trois heures précédant le coucher et inférieur ou égal à 1 lux pendant le sommeil, au niveau des yeux des occupants, dans toutes les zones concernées du bâtiment où une occupation résidentielle est prévue (voir Définitions). | L36: Avoir au moins 1 crédit pour la lumière naturelle. Toutes les zones concernées doivent respecter un niveau d'éclairement spécifique exprimé en lux mélanopique EDI (Equivalent Daylight Illuminance). Le seuil est de 250 lux mélanopique EDI pendant au moins 4 heures durant la journée (débutant au plus tard à midi). Modulation du Flux et du Spectre Le système d'éclairage électrique doit être capable d'ajuster son flux et sa sortie spectrale (Tunable White). Objectif : Permettre une réduction de l'EDI mélanopique l'après-midi et le soir afin de respecter les besoins physiologiques des occupants selon l'usage du bâtiment.
A37: Hea 04 | B37: Prérequis | C37: 1 | D37: APS-APD-PRO-DCE | E37: Pass | F37: 0 | G37: 0 | H37: 0 | I37: 0 | K37: 1. Les matériaux contenant de l'amiante ne doivent pas être prescrits ou installés. | L37: Les matériaux contenant de l'amiante ne doivent pas être prescrits ou installés.
A38: Hea 04 | B38: Plan de qualité de l'air intérieur (QAI) | C38: 2 | D38: APS-APD-PRO-DCE | E38: Very Good | F38: 0 | G38: 0 | H38: 0 | I38: 1 | J38: Plan QAI à vérifier | K38: 2. Un plan de qualité de l'air intérieur spécifique au site a été élaboré conformément à la note d'orientation 6 (GN06). Ce plan oriente la conception, les spécifications et l'installation afin d'optimiser l'amélioration de la qualité de l'air intérieur pendant l'occupation. Le plan doit prendre en compte les éléments suivants : 2.a Suppression des sources de contamination importantes 2.b Dilution et contrôle des autres sources de contamination, notamment : 2.b.i Exigences de qualité de l'air des zones spécialisées telles que les laboratoires, le cas échéant 2.c Procédures de purge et de renouvellement d'air avant occupation 2.d Tests et analyses effectués par un tiers 2.e Maintien de la qualité de l'air intérieur pendant l'utilisation 2.f Tout plan ou politique pertinent des autorités locales ou nationales (par exemple, zones de gestion de la qualité de l'air ou plans d'action locaux pour la qualité de l'air) | L38: Un plan de la qualité de l'air intérieur a été élaboré et mis en œuvre, avec l'objectif de faciliter un processus qui mène à concevoir, spécifier et implémenter des décisions d'installation et des actions qui minimisent la pollution de l'air intérieur.
A39: Hea 04 | B39: Ventilation | C39: 3-7 | D39: APS-APD-PRO-DCE | E39: Very Good (critère 7) | F39: 0 | G39: 0 | H39: 0 | I39: 1 | K39: Le bâtiment a été conçu pour minimiser la concentration et la recirculation des polluants à l'intérieur, comme suit : 3. Assurer l'apport d'air frais dans le bâtiment conformément à l'une des normes de bonnes pratiques en matière de ventilation énumérées ci-dessous (pour plus d'informations, voir M1.1) : 3.a ISO 17772-1:2017 Annexe I 3.b EN 16798-1:2019 Annexe B.3 3.c Norme nationale de bonnes pratiques en matière de ventilation. 4. Les voies de ventilation sont conçues pour minimiser la pénétration et l'accumulation de polluants atmosphériques à l'intérieur du bâtiment (voir M1.2). 5. Le cas échéant, les systèmes CVC doivent intégrer une filtration appropriée pour minimiser la pollution de l'air extérieur, telle que définie dans la norme EN 16798-1:2025, section B.4.2.(17). Les filtres spécifiés doivent atteindre une classification de l'air soufflé d'au moins SUP 2. Le niveau de filtration requis dépend de la qualité de l'air extérieur. 5.a Les immeubles résidentiels collectifs équipés de systèmes de climatisation centralisée peuvent démontrer leur conformité avec une classe de filtration F7 ou ePM1 50 %. 6 Les espaces occupés sont équipés de capteurs de dioxyde de carbone (CO₂) ou de capteurs de qualité de l'air étalonnés dans des zones spécifiques, conformément à la norme M1.3 et : 6.a Dans les bâtiments ou espaces ventilés mécaniquement : les capteurs sont reliés au système de ventilation mécanique et assurent une ventilation à la demande. 6.b Dans les bâtiments ou espaces ventilés naturellement : les capteurs peuvent alerter le propriétaire ou le gestionnaire du bâtiment lorsque les niveaux de CO₂ dépassent le seuil recommandé, ou sont reliés à des dispositifs de contrôle permettant d'ajuster la quantité d'air frais par exemple, des fenêtres à ouverture automatique ou des aérateurs de toiture. 6.c Le nombre total de capteurs et la surface intérieure nette des zones concernées couvertes par les capteurs sont déclarés via la plateforme BREEAM. 7 Dans les pays ou juridictions où fumer dans les bâtiments n’est pas interdit par la loi (voir Définitions), une interdiction de fumer couvrant toutes les zones publiques et réservées au personnel du bâtiment est mise en œuvre, et des panneaux « Interdit de fumer » sont placés dans des zones appropriées clairement visibles par tous les occupants (c.-à-d. les zones communes, les bureaux et les entrées du bâtiment). | L39: Les systèmes de ventilation minimisent la concentration de polluants dans le bâtiment, selon la norme EN ISO 17772-1 et EN 16798-1 sur les prises et rejets d'air, la filtration, et pour les espaces adéquat, un contrôle du CO2. Notamment 7 l/s/pers.
A40: Hea 04 | B40: Niveaux d'émission de composés organiques volatils (COV) (produits) | C40: 8-9 | D40: APS-APD-PRO-DCE | E40: - | F40: 0 | G40: 0 | H40: 0 | I40: 1 | K40: Pour un crédit : 8. Trois des cinq types de produits satisfont aux limites d'émission, aux exigences d'essai et à toutes les exigences supplémentaires énumérées dans le tableau 17 et le document M2. Lorsque les produits à base de bois ne font pas partie des trois types de produits sélectionnés, tous les produits à base de bois utilisés pour les aménagements et accessoires intérieurs doivent être testés et classés au minimum comme étant de classe E1 pour le formaldéhyde (voir CN2.2). Pour deux crédits : 9. Tous les types de produits satisfont aux limites d'émission, aux exigences d'essai et à toutes les exigences supplémentaires énumérées dans le tableau 17 et le document M2. | L40: 3 catégories sur 5 des éléments en contact avec l'air intérieur (peintures, vernis, produits en bois, revêtements de sol, faux plafonds, isolants thermiques et acoustiques, colles et joints) doivent respecter des seuils d'émission dans l'air intérieur pour les COVT ( ≤ 1.0 mg/m³), les formaldéhydes (≤ 0.06 mg/m³) et les produits cancérigènes 1A et 1B (≤ 0.001 mg/m³). (2 points si toutes les catégories valident le niveau)
A41: Hea 04 | B41: Mesures de qualité de l'air | C41: 10-16 | D41: APS-APD-PRO-DCE | E41: - | F41: 0 | G41: 0 | H41: 0 | I41: 1 | K41: 10. Le critère 2 a été atteint. 11. La concentration de formaldéhyde dans l'air intérieur est mesurée après la construction (mais avant l'occupation) et ne dépasse pas 100 µg/m³, en moyenne sur 30 minutes.(18) 12. L'échantillonnage et l'analyse du formaldéhyde sont effectués conformément aux normes ISO 16000-2(19) et ISO 16000-3(20) et à la méthodologie M3. 13. La concentration totale de composés organiques volatils (COVT) dans l'air intérieur est mesurée après la construction (mais avant l'occupation) et ne dépasse pas 300 µg/m³, en moyenne pondérée sur 8 heures.(21) 14. L'échantillonnage et l'analyse des COVT sont effectués conformément aux normes ISO 16000-5(22) et ISO 16000-6(23) ou ISO 16017-1(24) et à la méthodologie M3. 15. Lorsque les niveaux dépassent ces limites, l’équipe de projet confirme les mesures qui ont été ou seront prises conformément aux recommandations du plan QAI afin de réduire les niveaux de COVT et de formaldéhyde dans les limites susmentionnées. 16. Les concentrations mesurées de formaldéhyde (µg/m³) et de COVT (µg/m³) sont communiquées via la plateforme BREEAM. | L41: Les niveaux de concentration de Formaldéhyde ET de Composants Organiques Volatiles Totaux (TVOC) sont mesurés postconstruction et inférieurs à un seuil (respectivement ≤ 100µg/m³ et ≤ 300µg/m³).
A42: Hea 04X | B42: Exemplaire Niveaux d'émission de composés organiques volatils (COV) (produits) | C42: 17-18 | D42: APS-APD-PRO-DCE | E42: - | F42: 0 | G42: 0 | H42: 0 | I42: 1 | K42: Un crédit exemplaire 17 Au moins quatre des cinq types de produits énumérés dans le tableau 18 à la page 112 respectent les limites d'émission, les exigences d'essai et toutes les exigences supplémentaires énumérées dans le tableau 18 et M2. Deux crédits exemplaires 18 Tous les types de produits respectent les limites d'émission, les exigences d'essai et toutes les exigences supplémentaires énumérées dans le tableau 18 et M2. | L42: 4 catégories sur 5 des éléments en contact avec l'air intérieur (peintures, vernis, produits en bois, revêtements de sol, faux plafonds, isolants thermiques et acoustiques, colles et joints) doivent respecter des seuils d'émission dans l'air intérieur pour les COVT ( ≤ 0.3 mg/m³), les SCOVT (≤ 0.1 mg/m³) les formaldéhydes (≤ 0.01 mg/m³) et les produits cancérigènes 1A et 1B (≤ 0.001 mg/m³). (Toutes les catégories pour 2 points)
A43: Hea 05 | B43: Modélisation thermique - climat actuel | C43: 1-5 | D43: APS-APD-VISA-DET | E43: - | F43: 0 | G43: 0 | H43: 0 | I43: 1 | J43: STD ok, confirmer le périmètre avec Adrien | K43: 1. Calculer le confort thermique dans les zones occupées concernées à l'aide d'une simulation dynamique complète du bâtiment (voir M1.2). Procéder ainsi conformément à une norme approuvée ci-dessous, en tenant pleinement compte des variations saisonnières. Pour les bâtiments climatisés : 2. Le bâtiment est conçu pour répondre aux critères de confort thermique, selon l'une des méthodologies suivantes : 2.a Les niveaux de confort thermique dans les espaces occupés satisfont aux exigences de la catégorie B définies dans le tableau A.1 de l'annexe A de la norme ISO 7730:2005.(42) 2.b Norme ANSI/ASHRAE 55:2023. 2.c Autre norme sectorielle appropriée (lorsqu'elle définit une exigence ou un niveau plus élevé ou plus approprié pour le type de bâtiment), voir CN1.5. 3 Une fois générés, les indices PMV et PPD basés sur la modélisation ci-dessus doivent être communiqués via la plateforme BREEAM (voir CN1.3 et CN1.4). Pour les bâtiments à ventilation naturelle et les bâtiments à ventilation mécanique avec refroidissement de confort limité : 4. Les plages de températures opératives hivernales dans les espaces occupés sont conformes aux critères définis dans le Guide A de la CIBSE Conception environnementale, OU à toute autre norme sectorielle appropriée (lorsqu'elle définit une exigence ou un niveau plus élevé ou plus approprié pour le type de bâtiment). 5. Le bâtiment est conçu pour limiter le risque de surchauffe, en utilisant la méthodologie de confort adaptatif de l'une des normes suivantes : 5.a Norme ANSI/ASHRAE 55:2023. 5.b CIBSE TM59 : Méthodologie de conception pour l'évaluation du risque de surchauffe dans les logements. 5.c CIBSE TM52 : Les limites du confort thermique : éviter la surchauffe dans les bâtiments européens. 5.d Guide A de la CIBSE. 5.e Toute autre norme sectorielle nationale ou locale appropriée permettant d'atteindre le même résultat (lorsqu'elle définit une exigence ou un niveau plus élevé ou plus approprié pour le type de bâtiment), voir CN1.5. | L43: Une Simulation Thermique Dynamique de confort est menée, avec les indicateurs PMV (predicted mean vote) et PPD (predicted percentage of dissatisfied) de la norme ISO 7730:2005. Le confort thermique respecte le niveau B de la norme.
A44: Hea 05 | B44: Modélisation thermique - climat futur | C44: 6-9 | D44: APS-APD-VISA-DET | E44: - | F44: 0 | G44: 0 | H44: 0 | I44: 1 | J44: STD ok, confirmer le périmètre avec Adrien + PMV, PPD | K44: 6. Les critères 1 à 5 sont atteints. 7. La modélisation thermique montre que les exigences pertinentes énoncées dans le critère 2 ou 5 sont satisfaites pour un environnement climatique projeté (voir M1.3). 8. Lorsque le critère 7 ci-dessus n'est pas satisfait, l'équipe de projet démontre comment le bâtiment a été adapté, ou conçu pour être facilement adaptable à l'avenir grâce à des solutions de conception passive afin de satisfaire aux exigences du critère 7. 9. Pour les bâtiments climatisés, les indices PMV et PPD, calculés à partir de la modélisation ci-dessus, doivent être communiqués via la plateforme BREEAM (voir CN1.3 et CN1.4). | L44: Respecter les mêmes consignes que pour la modélisation thermique mais sur un scénario de changement climatique.
A45: Hea 05 | B45: Zonages et contrôles thermiques | C45: 10-12 | D45: APS-APD-PRO-DCE | E45: - | F45: 0 | G45: 0 | H45: 0 | I45: 1 | K45: 10. Les critères 1 à 5 sont atteints. 11. L'analyse de modélisation thermique (critères 1 à 5) a permis d'élaborer la stratégie de régulation de la température du bâtiment et de ses occupants. 12. La stratégie de chauffage ou de refroidissement proposée montre qu'elle prend en compte : 12.a Le zonage thermique du bâtiment et la manière dont les équipements techniques permettront de chauffer ou de refroidir efficacement et de façon appropriée ces zones. 12.b Le niveau de contrôle requis par l'utilisateur pour ces zones, adapté aux besoins des utilisateurs finaux (voir M2.1). La stratégie tient compte des éléments suivants : 12.b.i La connaissance des équipements techniques par l'utilisateur. 12.b.ii Le niveau de contrôle requis en fonction du type d'occupation, des habitudes et des fonctions des pièces (voir M2.2). 12.b.iii La manière dont l'utilisateur est susceptible d'utiliser les systèmes de chauffage ou de refroidissement. 12.b.iv Les attentes des utilisateurs selon les saisons et le niveau de contrôle individuel souhaité. 12.c En cas de présence de plusieurs systèmes, décrire comment les systèmes proposés interagiront et s'imbriqueront entre eux et comment cela pourrait affecter le confort thermique des occupants du bâtiment. 12.d Indiquer la nécessité, ou non, d'une commande manuelle accessible à l'utilisateur pour tout système automatique. | L45: Le zonage thermique est en accord avec le comportement du bâtiment et correspond aux données d'entrée de la STD.
A46: Hea 06 | B46: Prérequis | C46: 1 | D46: APS-APD-PRO-DCE | E46: - | F46: 0 | G46: 0 | H46: 0 | I46: 1 | J46: Ok retour MOA | K46: 1. Un acousticien qualifié (AQ ou SQA en anglais) est désigné par le client au stade approprié du processus d'acquisition (mais au plus tard après la finalisation de la conception préliminaire) afin de fournir des conseils préliminaires sur les points suivants : 1.a Les sources de bruit externes affectant le site choisi. 1.b L'aménagement du site et le zonage du bâtiment pour une acoustique optimale. 1.c Les exigences acoustiques pour les utilisateurs ayant des besoins spécifiques en matière d'audition et de communication. 1.d Le traitement acoustique des différentes zones et façades. | L46: Un acousticien est missionné sur le projet.
A47: Hea 06 | B47: Bruit ambiant intérieur (hors résidentiel) | C47: 2-4 | D47: APS-APD-VISA-DET | E47: - | F47: 1 | G47: 0 | H47: 0 | I47: 1 | J47: Intervention de l'acousticien | K47: 2. Tous les espaces inoccupés respectent les objectifs de niveau de bruit ambiant intérieur, tels que détaillés dans le critère le plus rigoureux 2.a ou 2.b ci-dessous : 2.a Objectifs de niveau de bruit ambiant intérieur définis par la réglementation nationale du bâtiment ou d’autres normes de bonnes pratiques appropriées. 2.b Lorsque la réglementation nationale du bâtiment ou les normes de bonnes pratiques n’existent pas pour le type de bâtiment ou ne fournissent pas d’objectifs de niveau de bruit ambiant intérieur, les niveaux de bruit ambiant intérieur sont conformes aux critères de « bonnes pratiques » décrits dans le tableau 20 à la page suivante. 3. Un organisme de certification (SQA) effectue des mesures de bruit ambiant pour s’assurer que les espaces concernés atteignent les niveaux requis. Si les mesures révèlent que des espaces ne respectent pas les normes, des travaux de remise en état sont effectués et les mesures sont répétées pour confirmer que les niveaux sont atteints avant la livraison et l’occupation. Établissements scolaires uniquement : 4. Les espaces d’enseignement et d’apprentissage dotés de toitures légères et de verrières doivent démontrer que les niveaux de pression acoustique réverbérée dans ces pièces ne dépassent pas de plus de 25 dB les limites appropriées indiquées dans le tableau 20 à la page suivante. | L47: Les niveaux de bruit ambiant interne et externe respectent les codes de bonne pratique. Une mesure à réception est effectuée pour l'attester. (Bureaux à occupation multiple 40-50 dB LAeqT)
A48: Hea 06 | B48: Isolation acoustique (hors résidentiel) | C48: 5-6 | D48: APS-APD-VISA-DET | E48: - | F48: 0 | G48: 0 | H48: 0 | I48: 1 | K48: 5 L’isolation acoustique entre les pièces sensibles sur le plan acoustique et les autres zones occupées est conforme aux exigences de confidentialité telles que détaillées dans le critère le plus rigoureux 5.a ou 5.b ci-dessous : 5.a L’isolation acoustique entre les pièces sensibles sur le plan acoustique et les autres zones occupées est conforme aux objectifs fixés par la réglementation nationale ou d’autres normes de bonnes pratiques appropriées. OU 5.b Lorsque la réglementation nationale ou les normes de bonnes pratiques applicables ne sont pas en vigueur pour le type de bâtiment ou ne définissent pas d'objectifs de performance en matière d'isolation acoustique, l'isolation acoustique entre les pièces sensibles à l'acoustique et les autres zones occupées est conforme au potentiel de confidentialité de la parole suivant : Dw + LAeqT > 75. 5.c Lorsque la confidentialité est jugée essentielle par le client ou l'équipe de conception (par exemple, cabinet médical, salle de consultation dans une banque) ou lorsque la pièce est adjacente à un espace bruyant comme une salle de musique, la zone doit être conforme à un potentiel de confidentialité de la parole renforcé : Dw + LAeqT > 85. 6 Les niveaux de pression acoustique de la pièce source et de la pièce réceptrice à partir desquels Dw est déterminé sont mesurés conformément à la norme (EN) ISO 16283-1:2014+A1:2017 et évalués conformément à la norme (EN) ISO 717-1:2020. Les mesures effectuées par la SQA doivent être basées sur des pièces finies mais non meublées, en tenant compte et en incluant l'effet de toute moquette et de tout plafond absorbant acoustiquement spécifié. | L48: L'isolation acoustique interne et externe respectent les codes de bonne pratique. Une mesure à réception est effectuée pour l'attester. (Dw + LAeqT > 75 hors locaux spécifiques)
A49: Hea 06 | B49: Temps de réverbération (hors résidentiel) | C49: 7 | D49: APS-APD-VISA-DET | E49: - | F49: 0 | G49: 0 | H49: 0 | I49: 0 | K49: 7. Les salles ou espaces utilisés pour la prise de parole (y compris les salles de réunion et les salles de discours) ou les salles utilisées pour la musique (représentations et répétitions) doivent atteindre les temps de réverbération détaillés dans le critère le plus rigoureux 7.a OU 7.b et 7.c, tels que mesurés par la SQA : 7.a Démontrer que le temps de réverbération ou la surface d’absorption équivalente des espaces concernés est conforme aux objectifs des réglementations nationales applicables ou d’autres normes de bonnes pratiques appropriées. 7.b Lorsque les réglementations nationales applicables ou les normes de bonnes pratiques n’exigent pas le contrôle du temps de réverbération, atteindre les temps de réverbération conformes au tableau 21 de la page suivante. 7.c Si cela concerne le bâtiment évalué, toutes les zones utilisées à des fins d’enseignement, de formation et d’éducation doivent atteindre les temps de réverbération conformes au tableau 22 de la page suivante. | L49: Les temps de réverbération ou les aires d'absorption équivalente respecte les codes de bonne pratique.
A50: Hea 06 | B50: Performance acoustique pour les bâtiments résidentiels | C50: 8-10 | D50: APS-APD-PRO-DCE | E50: - | F50: 0 | G50: 0 | H50: 0 | I50: 0 | K50: 8. Le bâtiment satisfait aux normes de performance acoustique et aux exigences d'essais détaillées dans la version la plus rigoureuse : SOIT : 8.a Les valeurs d'isolation aux bruits aériens et d'impact sont conformes aux normes d'amélioration des performances, par rapport à la réglementation nationale applicable décrite dans le tableau 23 à la page suivante ; OU 8.b Les niveaux d'isolation aux bruits aériens et d'impact sont conformes aux normes de performance décrites dans le tableau 24 à la page 133, sauf indication contraire dans les présents critères. 9. Un programme d'essais avant réception est réalisé par la SQA : SOIT : 9.a Selon le programme d'essais normal décrit dans la réglementation nationale applicable pour chaque groupe ou sous-groupe de pièces à usage d'habitation ; Il doit être démontré que les normes de performance détaillées dans ce document sont atteintes. OU 9.b En l'absence de réglementation nationale applicable, ou si celle-ci exige des mesures en laboratoire pour démontrer la conformité, le programme d'essais sur site avant réception doit être réalisé conformément aux recommandations relatives à la « Fréquence des essais requis » (voir les procédures de calcul dans la section Méthodologie, page 133) pour chaque groupe ou sous-groupe de pièces. 10 Le nombre de crédits accordés dépendra de l'amélioration apportée à la réglementation nationale, déterminée selon le tableau 23 (page suivante) ou le tableau 24 (page 133). Lorsque des espaces commerciaux sont situés sous des espaces résidentiels, seuls des essais d'isolation acoustique aux bruits aériens seront requis. | L50: Le bâtiment respecte les normes de performances acoustiques et des tests sont effectués à réception.
A51: Hea 07 | B51: Accès sûr | C51: 1-6 | D51: - | E51: - | F51: 1 | G51: 0 | H51: 0 | I51: 1 | J51: Séparation des flux impossible | K51: 1. Des pistes cyclables dédiées sont aménagées, respectant les dimensions minimales de largeur suivantes ou les recommandations locales en matière d'aménagement : 1.a Lorsque les voies piétonnes et cyclables sont partagées, la largeur totale minimale de la voie combinée est de 3,0 m. 1.b Lorsque la piste cyclable est séparée de la voie piétonne et de la chaussée, la largeur minimale de la piste cyclable est de 2,0 m et celle de la voie piétonne de 1,5 m. 1.c Lorsque la piste cyclable fait partie de la chaussée, sa largeur minimale est de 1,5 m. 2. Des cheminements piétonniers sécurisés et dédiés sont aménagés sur et autour du site, assurant des liaisons appropriées pour : 2.a L'entrée du site à l'entrée du bâtiment. 2.b Les parkings (le cas échéant) à l'entrée du bâtiment. 2.c Le bâtiment aux espaces extérieurs. 2.d Connexion aux cheminements extérieurs, le cas échéant. 2.e Les pôles de transport locaux et autres commodités extérieures (le cas échéant). 3. Les zones de dépose-minute pour piétons, lorsqu'elles sont prévues, sont aménagées à proximité de la voie d'accès et offrent un accès direct aux chemins piétonniers. Lorsque des zones d'accès et de dépose pour véhicules de livraison font partie du projet évalué, les dispositions suivantes s'appliquent : 4. Les zones de livraison ne sont pas accessibles directement par les parkings généraux et ne croisent ni ne partagent les éléments suivants : 4.a. Voies piétonnes et cyclables. 4.b. Espaces extérieurs accessibles aux usagers du bâtiment et au public. 5. Une zone de stationnement ou d'attente est réservée aux véhicules de livraison et correctement séparée de la zone de manœuvre et du parking du personnel et des visiteurs. 6. Les zones de stationnement et de retournement sont conçues pour faciliter les manœuvres en fonction du type de véhicule de livraison susceptible d'accéder au site, évitant ainsi les manœuvres répétées | L51: Mise en place de pistes cyclables et cheminements piétons sûrs. Les zones de livraison permettent de manœuvrer simplement et ne croisent pas les autres flux.
A52: Hea 07 | B52: Bâtiment accessible (hors résidentiel) | C52: 7-9 | E52: - | F52: 1 | G52: 0 | H52: 0 | I52: 1 | J52: Pas d'étage nécéssite une étude | K52: 7. Le bâtiment est conçu pour être adapté à son usage, approprié et accessible à tous les utilisateurs potentiels. 8. Une stratégie d'accessibilité est élaborée conformément à la liste de contrôle A3 (page 420). Cette stratégie vise, au minimum, à garantir l'accès à l'ensemble du bâtiment pour tous les utilisateurs, en mettant l'accent sur les points suivants : 8.a. Les personnes en situation de handicap : des solutions de conception permettant de supprimer les obstacles liés au handicap sont proposées. 8.b. Les personnes de tous âges, sexes, origines ethniques et niveaux de mobilité. 8.c. Les parents accompagnés d'enfants (lorsque cela est pertinent compte tenu de l'usage ou du type de bâtiment). 9. Des équipements sont prévus pour les futurs occupants et utilisateurs du bâtiment (voir Définitions), notamment, le cas échéant, des équipements partageables et accessibles au public ou à la communauté sans permettre un accès non contrôlé à d'autres parties du bâtiment (sauf si les procédures de sécurité l'interdisent). | L52: Bâtiment inclusif dans son ensemble. Plus particulièrement pour: les personnes à mobilité réduite, toutes les tranches d'âge, origine, genre, forme physique, les personnes accompagnées d'enfants. Voir checklist A3. Une stratégie doit être mise en place
A53: Hea 07 | B53: Bâtiment accessible (résidentiel) | C53: 10 | E53: Outstanding | F53: 0 | G53: 0 | H53: 0 | I53: 0 | K53: 10. Le concepteur doit confirmer que le projet évalué est conforme aux exigences de la liste de contrôle Lifetime Homes (voir la liste de contrôle A4, page 421), soit : 10.a Respect des normes nationales de bonnes pratiques ou de la législation locale en vigueur qui couvrent (au minimum) les exigences de la liste de contrôle Lifetime Homes. OU 10.b Démontrer la conformité aux exigences de la liste de contrôle Lifetime Homes.
A54: Hea 07x | B54: Sureté du site et du bâtiment | C54: 11-13 | E54: - | F54: 1 | G54: 0 | H54: 0 | I54: 1 | J54: Option Hea07 | K54: 11. Un spécialiste en sécurité dûment qualifié (SSDQ) réalise une évaluation des besoins de sécurité (EBS) fondée sur des données probantes pendant ou avant la phase de conception préliminaire. L'EBS vise à identifier les caractéristiques du projet, du site et de ses environs qui peuvent influencer l'approche en matière de sécurité du développement. 12. Le SSDQ élabore un ensemble de mesures de sécurité et de recommandations à intégrer aux propositions. Ces mesures et recommandations doivent être directement liées aux menaces et aux actifs identifiés dans l'EBS précédente. 13. Les mesures et recommandations doivent être intégrées aux propositions et mises en œuvre dans le projet final. Toute dérogation à ces mesures et recommandations doit être justifiée et approuvée par le SSDQ. | L54: Un spécialiste de la sécurité et nommé et fait des recommandations sur le projet en phase de conception (APS). Les recommandations sont intégrées au projet. Des écarts sont possibles en consultant le spécialiste.
A55: Hea 09 | B55: Espaces privés (résidentiel) | C55: 1-2 | E55: Outstanding | F55: 0 | G55: 0 | H55: 0 | I55: 0 | K55: 1. L’espace extérieur (privé ou semi-privé) doit satisfaire aux exigences suivantes : 1.a. Il doit être suffisamment grand pour permettre à tous les occupants de s’asseoir à l’extérieur. 1.b. Il doit être accessible à tous les occupants, y compris aux personnes en fauteuil roulant. 1.c. Il doit être accessible uniquement aux occupants des logements désignés. 2. Les espaces extérieurs doivent être adjacents aux logements ou situés à proximité immédiate de ceux-ci et respecter les dimensions minimales requises. (voir M1).
A56: Hea 10 | B56: Risques Naturels | C56: 1-2 | D56: ESQ-APS-APD | E56: - | F56: 1 | G56: 1 | H56: 1 | I56: 1 | J56: option Hea10 | K56: 1. Une évaluation des risques est réalisée, dès l'étape de la proposition préliminaire ou de la conception préliminaire, par une ou plusieurs personnes compétentes afin d'identifier les risques naturels potentiels dans la zone de développement. 2. Lorsqu'un risque potentiel est identifié, une personne compétente doit définir et mettre en œuvre des mesures d'atténuation adaptées au niveau de risque. | L56: Une évaluation des risques est menée en ESQ ou APS. Lorsqu’un danger potentiel est identifié, des mesures d’atténuation correspondant au niveau de risque doivent être identifiées par une personne appropriée et mises en œuvre.
A57: Hea 11 | B57: Qualité de l'eau | C57: 1-4 | E57: Pass (critère 1) | F57: 0 | G57: 0 | H57: 0 | I57: 1 | K57: Minimisation des risques de contamination 1 Tous les systèmes d'eau du bâtiment sont conformes aux bonnes pratiques et réglementations en vigueur en matière de santé et de sécurité afin de minimiser les risques de contamination microbienne, notamment la légionellose. 2 Lorsqu'une humidification est nécessaire, un système d'humidification de sécurité est installé. Eau potable : tous types de bâtiments, à l'exception des résidences et des établissements d'hébergement (séjour de longue durée) : 3 Des fontaines à eau alimentent en eau potable les zones où du personnel est présent en permanence, notamment les zones suivantes le cas échéant : 3.a Cuisines du personnel. 3.b Cafétérias du personnel. 3.c Autres emplacements appropriés à chaque étage. De plus, pour les établissements d'hébergement et les établissements d'hébergement (séjour de courte durée) : 4 Des fontaines à eau alimentent en eau potable les espaces communs : 4.a Si de l'eau potable est disponible dans chaque chambre, une fontaine à eau est accessible depuis tous les principaux espaces communs. 4.b Si l'eau potable n'est pas disponible dans chaque chambre, une fontaine à eau est accessible depuis tous les principaux espaces communs ET est spécifiée dans les espaces communs à proximité des principaux points d'accès (ascenseurs et cages d'escalier) à chaque étage ou zone de chambres. | L57: Conception minimisant le risque de contamination microbienne dans le système de distribution d'eau. Mise à disposition d'eau potable saine dans tous les espaces occupés de façon permanente
A58: Ene 01 | B58: Performance énergétique | C58: 1 | D58: APS-APD-VISA-DET | E58: Excellent (4 crédits) Outstanding (6 crédits) | F58: 9 | G58: 4 | H58: 6 | I58: 8 | J58: Sur calcul RE2020 | K58: 1. Calculer le coefficient de performance énergétique global (EPR_INC) selon les modalités suivantes : 1.a Option 1 – Amélioration des performances par rapport à la réglementation locale du bâtiment : Il existe une méthode de calcul nationale (NCM) dans le pays d’évaluation permettant à l’équipe de conception de réaliser une analyse complète des performances énergétiques. Voir M2.1. 1.b Option 2 – Amélioration des performances par rapport aux valeurs de référence ASHRAE : L’analyse des performances énergétiques est réalisée à l’aide d’un logiciel alternatif agréé, en comparaison avec les valeurs de référence ASHRAE pertinentes. Voir M2.2. Pour les deux options, le nombre de crédits BREEAM attribués est indiqué dans le tableau 26. | L58: Les points s'obtiennent en fonction de la performance sur le calcul RE2020. Plus le Cep du projet est bas, plus le nombre de points attribués est important.
A59: Ene 01X | B59: Zéro net carbone | C59: 2-3 | D59: APS-APD-VISA-DET | E59: - | F59: 0 | G59: 0 | H59: 0 | I59: 0 | J59: pas de PV? | K59: 2. Le bâtiment a été modélisé selon l'option 1 ou l'option 2, et les résultats de la modélisation démontrent qu'au moins 100 % des besoins énergétiques réglementés du bâtiment sont couverts par des technologies à faibles émissions de carbone ou à émissions nulles (voir M3). 3. Le nombre de crédits BREEAM attribués est calculé en fonction du pourcentage de la consommation énergétique opérationnelle du bâtiment couvert par des sources à faibles émissions de carbone ou à émissions nulles (voir tableau 27 ci-dessous). | L59: Tous les usages RT sont couverts par une production d'énergie renouvelable locale et les autres usages sont couverts à 0 / 50 / 100% par une production d'énergie renouvelable locale
A60: Ene 02 | B60: Prérequis | C60: 14 | E60: Outstanding | F60: 0 | G60: 0 | H60: 0 | I60: 0 | J60: Pré-requis uniquement pour l'outstanding, pas de gaz sur site | K60: 14. Aucune énergie fossile ne sera utilisée dans le bâtiment en exploitation (sauf pour du process spécifique) | L60: Aucune énergie fossile dans le bâtiment (sauf pour du process spécifique)
A61: Ene 02 | B61: Stratégie énergétique | C61: 1 | E61: - | F61: 0 | G61: 0 | H61: 0 | I61: 1 | J61: sur étude STD / SED | K61: 1. Définir une stratégie énergétique pour le bâtiment dès la phase de conception préliminaire, décrivant qualitativement comment les performances opérationnelles énergétiques et carbone du bâtiment seront minimisées (voir M1.1). | L61: Mise en place d'une stratégie énergétique pour le projet en phase APS. (enveloppe, systèment, ENR)
A62: Ene 02 | B62: Modélisation énergétique prédictive | C62: 2-4 | E62: Outstanding | F62: 0 | G62: 0 | H62: 0 | I62: 3 | J62: sur étude STD / SED | K62: 2. Estimer les consommations énergétiques non réglementées et les profils d'occupation du bâtiment (voir M1.2.1). 3. Élaborer un modèle énergétique détaillé lors de la phase de conception technique et réaliser une analyse de sensibilité et une modélisation de scénarios afin d'explorer l'impact des principaux paramètres et hypothèses sur la consommation énergétique (voir M1.2.2). 4. Prédire la consommation énergétique opérationnelle annuelle du bâtiment, par type de combustible, à partir de la modélisation de scénarios. La modélisation devra être mise à jour après la construction afin de prendre en compte toute modification du cahier des charges du bâtiment (voir M1.2.3 et M1.2.4). | L62: Un modèle énergétique du bâtiment a été réalisé et prévoit les consommations par usage avec différents scénarios.
A63: Ene 02 | B63: Evaluation et atténuation des risques | C63: 5-6 | E63: - | F63: 0 | G63: 0 | H63: 0 | I63: 1 | K63: 5. Obtenir les crédits relatifs à la modélisation énergétique prédictive. 6. Mettre en évidence les risques importants liés à la conception, aux aspects techniques et aux procédés susceptibles d'empêcher les bâtiments d'atteindre l'objectif de performance énergétique et indiquer comment ces risques seront atténués tout au long du processus de construction et de mise en service (voir M1.3). | L63: Une évaluation des risques de dérive énergétique a été menée. Il peut être prouvé que la performance énergétique a été sensiblement améliorée.
A64: Ene 02 | B64: Score de prédiction énergétique opérationnelle | C64: 7-8 | E64: Excellent (3 crédits) Outstanding (5 crédits) | F64: 0 | G64: 0 | H64: 0 | I64: 5 | J64: sur étude STD / SED et résultats | K64: 7. Obtenir les crédits de modélisation énergétique prédictive. 8. Les crédits sont attribués en fonction du score de performance énergétique opérationnelle des nouvelles constructions (OEPNC), comme indiqué dans le tableau 28 ci-dessous (voir M2). | L64: Un atelier d'optimisation énergétique a été mis en place. Il peut être prouvé que la performance énergétique a été sensiblement améliorée. La plateforme BREEAM attribue un nombre de point selon la performance de la SED.
A65: Ene 02X | B65: Publication d'un objectif de performance énergétique | C65: 9 | E65: - | F65: 0 | G65: 0 | H65: 0 | I65: 1 | K65: 1. Un objectif de performance énergétique en exploitation a été communiqué aux parties prenantes et rendu public avant la réception des travaux (M3). | L65: Un objectif de performance énergétique en exploitation a été communiqué aux parties prenantes et rendu public avant la réception des travaux
A66: Ene 02X | B66: Validation du modèle par un tiers | C66: 10 | E66: - | F66: 0 | G66: 0 | H66: 0 | I66: 1 | K66: 10. Les résultats de la modélisation de la consommation énergétique prédictive ont fait l'objet d'une validation par une tierce partie indépendante | L66: Les résultats de la modélisation de la consommation énergétique prédictive ont fait l'objet d'une validation par une tierce partie indépendante
A67: Ene 02X | B67: Préparation de la phase exploitation | C67: 11-12 | E67: - | F67: 0 | G67: 0 | H67: 0 | I67: 1 | J67: etude à conformer avec le plan de comptage | K67: 11. Tous les points Ene03 Energy Monitoring sont acquis. 12. Les sorties de la modélisation énergétique incluent une ventilation de la consommation d'énergie par sous-compteur, alignée avec le plan de comptage du bâtiment. | L67: Tous les points Ene03 sont acquis. Les sorties de la modélisation énergétique incluent une ventilation de la consommation d'énergie par sous-compteur, alignée avec le plan de comptage du bâtiment.
A68: Ene 02X | B68: Engagement à mesurer la consommation réelle en exploitation | C68: 13 | E68: - | F68: 0 | G68: 0 | H68: 0 | I68: 1 | K68: 13. Le client ou l'occupant du bâtiment s'engage financièrement à faire mesurer la consommation énergétique réelle par un assesseur énergétique dûment qualifié, une fois que le bâtiment atteint son seuil d'occupation. | L68: Le client ou l'occupant du bâtiment s'engage financièrement à faire mesurer la consommation énergétique réelle par un assesseur énergétique dûment qualifié, une fois que le bâtiment atteint son seuil d'occupation.
A69: Ene 03 | B69: Suivi de la consommation énergétique par usage final | C69: 1-5 | D69: APS-APD-VISA-DET | E69: Very Good | F69: 0 | G69: 0 | H69: 0 | I69: 1 | J69: Valider la mise en place d'un système de gestion de l'énergie compatible BACS | K69: 1. Identifier les sources d'énergie utilisées par le bâtiment et estimer la consommation énergétique annuelle pour les éléments suivants (voir M1) : 1.a Électricité du réseau 1.b Gaz du réseau 1.c Chauffage urbain 1.d Refroidissement urbain 1.e Électricité renouvelable produite sur site. 2. Un système de suivi de la consommation énergétique est installé, permettant d'attribuer au moins 90 % de la consommation énergétique annuelle estimée pour chaque source d'énergie à une catégorie d'utilisation finale (voir M2). 3. L'électricité renouvelable produite sur site et exportée du bâtiment doit faire l'objet d'un suivi distinct. 4. Un système de comptage de l'énergie adapté à la taille du bâtiment est installé : 4.a Pour les bâtiments d'une surface intérieure brute ≥ 1 000 m², les compteurs d'énergie sont connectés à un système de suivi et de gestion de l'énergie. 4.b Pour les bâtiments d'une surface intérieure brute < 1 000 m², les compteurs d'énergie sont soit : 4.b.i Connectés à un système de suivi et de gestion de l'énergie approprié. OU 4.b.ii Les compteurs sont-ils accessibles et dotés de sorties à impulsions ou d’autres sorties de communication à protocole ouvert ? 5 Les personnes chargées du suivi de la consommation énergétique du bâtiment peuvent identifier clairement la catégorie d’utilisation finale couverte par chaque compteur. | L69: Les systèmes de mesure de l'énergie installés permettent d'assigner 90% de la consommation énergétique de chaque source à une catégorie d'utilisation finale. Un système de contrôle et de gestion de l'énergie est installé. Les services consommateurs d'énergie sont identifiables par les utilisateurs du bâtiment.
A70: Ene 03 | B70: Suivi de la consommation énergétique pour différents occupants et zones fonctionnelles | C70: 6-8 | D70: APS-APD-VISA-DET | E70: - | F70: 0 | G70: 0 | H70: 0 | I70: 1 | J70: Valider la mise en place d'un système de gestion de l'énergie compatible BACS | K70: 6. Un système de suivi de la consommation énergétique est installé, permettant d'attribuer la consommation d'énergie aux zones louées ou occupées séparément et aux zones fonctionnelles concernées au sein du bâtiment (voir M3). 7. Un système de comptage de l'énergie adapté à la taille du bâtiment est installé : 7.a. Pour les bâtiments d'une surface intérieure brute ≥ 1 000 m², les compteurs d'énergie doivent être connectés à un système de suivi et de gestion de l'énergie. 7.b. Pour les bâtiments d'une surface intérieure brute < 1 000 m², les compteurs d'énergie sont soit : 7.b.i. Connectés à un système de suivi et de gestion de l'énergie approprié. OU 7.b.ii. Des compteurs accessibles avec sorties à impulsions ou autres sorties de communication à protocole ouvert. 8. Les personnes responsables du suivi de la consommation énergétique du bâtiment peuvent identifier clairement la zone fonctionnelle ou d'occupation couverte par chaque compteur. | L70: Un système de surveillance et de gestion de l'énergie accessible ou des compteurs d'énergie accessibles séparés avec un signal de sortie impulsionnel ou d'autres protocoles de communication ouverts pour permettre une future connexion à un système de surveillance et de gestion de l'énergie sont fournis.
A71: Ene 04 | B71: Optimisation de la forme du bâtiment | C71: 1-2 | D71: ESQ | E71: - | F71: 1 | G71: 0 | H71: 1 | I71: 0 | J71: Nécessite de lancer l'étude Ene04 dès cette phase | K71: 1. Analyse effectuée dès le stade Concept (esquisse) pour explorer l'effet de la forme architecturale sur la demande énergétique. 2. Il faut prouver que cette étude a réellement influencé le design final. | L71: Analyse effectuée dès le stade Concept (esquisse) pour explorer l'effet de la forme architecturale sur la demande énergétique. Il faut prouver que cette étude a réellement influencé le design final.
A72: Ene 04 | B72: Optimisation de l'enveloppe du bâtiment | C72: 3-8 | D72: ESQ | E72: - | F72: 2 | G72: 0 | H72: 2 | I72: 2 | K72: 3. Analyse obligatoire : Comparer différentes spécifications de parois (isolation, vitrage) pour réduire les besoins de chauffage et refroidissement. 4-5. Option A (1 crédit) : Réduction de la demande de chauffage/froid de 5% par rapport à la réglementation locale. 6-7. Option B (2 crédits) : Réduction de la demande de chauffage/froid de 10% par rapport à la réglementation locale. 8. Option C (2 crédits) : Démontrer que l'enveloppe a été optimisée au maximum techniquement possible (M2). | L72: Analyse obligatoire : Comparer différentes spécifications de parois (isolation, vitrage) pour réduire les besoins de chauffage et refroidissement. Option A : Réduction de la demande de chauffage/froid de 5% par rapport à la réglementation locale. Option B : Réduction de la demande de chauffage/froid de 10% par rapport à la réglementation locale. Option C : Démontrer que l'enveloppe a été optimisée au maximum techniquement possible.
A73: Ene 04 | B73: Production d'énergie bas carbone | C73: 9-11 | D73: ESQ | E73: - | F73: 2 | G73: 2 | H73: 2 | I73: 1 | J73: 40% de surface de la toiture couverte conformément à la réglementation | K73: Un crédit – Installation de technologies de production d'énergie LZC 9 Une ou plusieurs technologies de production d'énergie LZC éligibles ont été installées par des installateurs compétents. Un crédit – Respect des objectifs de production d'énergie LZC 10 Obtenir le crédit « Installation de technologies de production d'énergie LZC » (critère 9). 11 L'énergie produite par les technologies de production d'énergie LZC installées doit respecter les objectifs suivants : 11.a Lorsque les panneaux photovoltaïques (PV) sont la seule technologie de production d'énergie LZC installée, l'électricité produite doit : 11.a.i Être égale ou supérieure à celle produite par des panneaux PV de référence couvrant 50 % de la surface du rez-de-chaussée. OU 11.a.ii Représenter au moins 60 % de la consommation annuelle d'électricité du bâtiment. 11.b Lorsque seules des technologies de production d'énergie LZC autres que les panneaux PV sont installées, l'énergie produite doit : 11.b.i Être égale ou supérieure à 137 kWh/an/m² de surface du rez-de-chaussée. OU 11.b.ii Satisfaire au moins 60 % de la demande annuelle du bâtiment pour la source d’énergie concernée. 11.c Lorsque les technologies de production d’énergie à faible consommation d’énergie installées comprennent à la fois des panneaux photovoltaïques et d’autres technologies de production d’énergie à faible consommation d’énergie, les objectifs de production sélectionnés, tels qu’indiqués en 11.a et 11.b, doivent être utilisés conjointement et ajustés proportionnellement à la quantité d’électricité produite par chaque technologie (voir M3.4). | L73: Premier crédit : installation d'une production d'énergie renouvelable locale. Deuxième crédit : production d'au moins 60% de la consommation annuelle du bâtiment.
A74: Ene 05 | B74: Performance énergétique des équipements | C74: 1-4 | D74: APS-APD-VISA-DET | E74: - | F74: 0 | G74: 0 | H74: 0 | I74: 3 | J74: Calcul à faire | K74: 1. Identifier les éléments consommateurs d'énergie non réglementée (c'est-à-dire hors tertiaire : CVC, éclairage et ECS, voir M1). Exemples d'équipements : Réfrigérateurs / Congélateurs / Lave-linge / Sèche-linge / Climatiseurs individuels / Écrans d'ordinateur / Lave-vaisselle / Téléviseurs 2. Estimer la consommation énergétique annuelle prévue des équipements concernés identifiés au critère 1 (voir M2). 3. Déterminer le ratio entre la consommation d'énergie "non-réglementée" et la consommation d'énergie "réglementée" des équipements concernés afin de calculer le nombre de crédits disponibles (voir tableau 30 ci-dessous et M3). 4. Déterminer quels équipements concernés sont économes en énergie (voir M4). | L74: Le nombre de crédits dépend du ratio entre la consommation énergétique des équipements hors RE/RT et la consommation RE/RT. De 1 à 5 par tranche de 10% jusqu'à 40%. Les équipements industriels / temporaires / utilisé uniquement pour les situations d'ugence / existants / mobiles sont exclus de l'évaluation. Il en va de même pour les équipements pour lesquels le coût de l'amélioration de la performance est supérieur à l'économie réalisée. Exemples de systèmes : Le nombre de point atteint est proportionnel à la consommation des équipements "performants" sur la consommation totale des équipements du périmètre. Exemples d'équipements : Réfrigérateurs / Congélateurs / Lave-linge / Sèche-linge / Climatiseurs individuels / Écrans d'ordinateur / Lave-vaisselle / Téléviseurs
A75: Ene 06 | B75: Performance énergétique des systèmes | C75: 1-4 | D75: APS-APD | E75: - | F75: 0 | G75: 0 | H75: 0 | I75: 5 | J75: Calcul à faire | K75: 1. Identifier les systèmes consommateurs d'énergie "non-réglementée" (voir M1). Exemple : Éclairage extérieur / Stockage frigorifique / Ascenseurs et escaliers mécaniques / Piscines / Blanchisseries / Systèmes de refroidissement dans les salles serveurs 2. Estimer la consommation énergétique annuelle prévue des systèmes concernés identifiés au critère 1 (voir M2). 3. Déterminer le ratio entre l'énergie "non-réglementée" consommée par les systèmes concernés et l'énergie réglementée consommée afin de calculer le nombre de crédits disponibles (voir tableau 32 ci-dessous et M3). 4. Identifier les systèmes concernés qui sont économes en énergie (voir M4). | L75: Le nombre de crédits dépend du ratio entre la consommation énergétique des systèmes hors RE/RT et la consommation RE/RT. De 1 à 9 par tranche de 10% jusqu'à 80%. Les systèmes industriels / temporaires / utilisé uniquement pour les situations d'ugence / existants / mobiles sont exclus de l'évaluation. Il en va de même pour les équipements pour lesquels le coût de l'amélioration de la performance est supérieur à l'économie réalisée. Le nombre de point atteint est proportionnel à la consommation des systèmes "performants" sur la consommation totale des systèmes du périmètre. Éclairage extérieur / Stockage frigorifique / Ascenseurs et escaliers mécaniques / Piscines / Blanchisseries / Systèmes de refroidissement dans les salles serveurs
A76: Ene 07 | B76: Réponse flexible à la demande | C76: 1-2 | E76: - | F76: 0 | G76: 0 | H76: 0 | I76: 0 | K76: 1. Identifier les systèmes installés sur site et leur capacité de réponse flexible à la demande. 2. Le nombre de crédits attribués dépend du nombre de crédits disponibles et du pourcentage de points de réponse flexible à la demande attribués (voir tableau 39). | L76: Les points se calculent en fonction du nombre de systèmes pouvant répondre aux signaux du fournisseur d'électricité (chauffage / refroidissement / bornes IRVE / ECS / autres systèmes (batteries))
A77: Ene 08 | B77: Commande des équipements | C77: 1-3 | E77: - | F77: 0 | G77: 0 | H77: 0 | I77: 1 | K77: 1. Déterminer le nombre de points de commande disponibles en fonction des services CVC installés et des détails du système concerné. 2. Déterminer le nombre de points de commande opérationnels en fonction de la fonctionnalité des commandes. 3. Le nombre de crédits accordés est déterminé par la proportion de points de commande opérationnels parmi les points disponibles (voir tableau 42 à la page suivante et M1). | L77: Jusqu'à 2 points en fonction des possibilités de contrôle des équipements de chauffage, refroidissement et ventilation.
A78: Tra 01 | B78: Evaluation de l'accessiblité en transport et plan de déplacement | C78: 1-2 | D78: ESQ | E78: - | F78: 2 | G78: 2 | H78: 2 | I78: 2 | J78: plan de déplacement à faire | K78: 1. Réaliser une évaluation des transports spécifique au site avant la fin de la phase de conception préliminaire : voir M1. 2. Élaborer un plan de mobilité spécifique au site, conformément aux recommandations de l’évaluation des transports, avant la fin de la phase de conception préliminaire : voir M3. 3. Démontrer que le plan de mobilité peut guider la mise en œuvre appropriée de mesures de transport durable lors des phases de conception, de construction et d’occupation, et qu’il peut être soutenu par la direction du bâtiment pendant son exploitation. | L78: Etude spécifique au site analysant l'accessibilité actuelle (transports en commun, réseaux cyclables, accès piétons) et les besoins futurs générés par le projet. Mise en place d'un plan de déplacement sur la base des conclusions de l'étude de site. A réaliser en APS.
A79: Tra 02a | B79: Mise en place de mesure pour les transports durables (non résidentiel) | C79: 1-2 | D79: ESQ | E79: - | F79: 10 | G79: 3 | H79: 4 | I79: 8 | J79: Construction d'un espace extérieur dimensionné pour les occupants Locaux vélos Option installation de bornes sur 10% des places + infrastrucutre sur 20% supplémentaire | K79: 1. Réalisez une évaluation des transports et un plan de déplacement conformément à Tra 01. Si ces documents sont finalisés après la phase de conception préliminaire, ils peuvent néanmoins être utilisés pour satisfaire à cette exigence. 2. Calculez les crédits comme suit : 2.a Reportez-vous au score de l’Indice d’accessibilité des transports publics (IATP) calculé dans Tra 01. Ce score servira à pondérer les points attribués dans Tra 02a. 2.b Attribuez des points pour les mesures de transport durable mises en œuvre dans Tra 02, conformément au tableau 48 (page 226). 2.c Utilisez le tableau 49 (page 226) pour convertir le nombre de points obtenus pour les mesures de transport durable en crédits, pondérés par le score IATP. | L79: Le crédit TRA01 doit être atteint. Le projet obtient des points en fonction des mesures de déplacement doux mise en place et de son niveau d'accessiblité en transport en commun. Mesures possibles : information sur les transports locaux dans le bâtiment, installation de bornes IRVE, favoriser l'auto-partage, emplacements vélos, douches et casiers, présence d'aménités)
A80: Tra 02b | B80: Mise en place de mesure pour les transports durables (résidentiel) | C80: 1-2 | D80: ESQ | E80: - | F80: 0 | G80: 0 | H80: 0 | I80: 0 | K80: 1. Réalisez une évaluation des transports et un plan de déplacement conformément à Tra 01. Si ces documents sont finalisés après la phase de conception, ils peuvent néanmoins être utilisés pour satisfaire à cette exigence. 2. Calculez les crédits comme suit : 2.a. Reportez-vous au score de l’Indice d’accessibilité des transports publics (IATP) calculé dans Tra 01. Ce score servira à pondérer les points attribués dans Tra 02b. 2.b. Attribuez des points pour les mesures de transport durable mises en œuvre dans Tra 02b, conformément au tableau 57 (page 243). 2.c. Utilisez le tableau 58 (page 243) pour convertir le nombre de points obtenus pour les mesures de transport durable en crédits, pondérés par le score IATP. | L80: Le crédit TRA01 doit être atteint. Le projet obtient des points en fonction des mesures de déplacement doux mise en place et de son niveau d'accessiblité en transport en commun. Mesures possibles : information sur les transports locaux dans le bâtiment, installation de bornes IRVE, favoriser l'auto-partage, emplacements vélos, douches et casiers, présence d'aménités)
A81: Wat 01 | B81: Consommation d'eau | C81: 1-3 | D81: APS-APD-VISA-DET | E81: Good (1 crédits) Outstanding (2 crédits) | F81: 0 | G81: 0 | H81: 0 | I81: 4 | J81: calcul selon l'outil | K81: 1. Déterminer l'efficacité hydrique de tous les composants consommateurs d'eau concernés. 2. Déterminer la quantité d'eau recyclée attendue des systèmes d'eaux noires, d'eaux grises et d'eaux pluviales approuvés. 3. Le nombre de crédits accordés est déterminé par le pourcentage d'amélioration de la consommation d'eau potable (en litres par personne et par jour) pour le bâtiment concerné par rapport à un bâtiment de référence (voir tableau 62). Pourcentage d'amélioration par rapport à la valeur de référence ≥ 15% pour 1 crédit, ≥ 75% pour 5 crédit | L81: Mise en place d'équipement hydro-économes dans les sanitaires. Le nombre de points atteints se calcule via un outil BREEAM spécifique.
A82: Wat 01X | B82: Niveau exemplaire | C82: 1-5 | D82: APS-APD-VISA-DET | E82: - | F82: 0 | G82: 0 | H82: 0 | I82: 0 | K82: 1. Déterminer l'efficacité hydrique de tous les composants consommateurs d'eau concernés. 2. Déterminer la quantité d'eau recyclée attendue des systèmes d'eaux noires, d'eaux grises et d'eaux pluviales approuvés. 3. Le nombre de crédits accordés est déterminé par le pourcentage d'amélioration de la consommation d'eau potable (en litres par personne et par jour) pour le bâtiment concerné par rapport à un bâtiment de référence (voir tableau 62). Pourcentage d'amélioration par rapport à la valeur de référence ≥ 85% pour obtenir un crédit supplémentaire en plus des 6 précédents. | L82: Atteinte d'une niveau de consommation d'eau potable exceptionnellement faible en utilisant des systèmes de type "récupération d'eau pluviale".
A83: Wat 02 | B83: Gestion de l'eau | C83: 1-4 | D83: APS-APD-PRO-DCE | E83: Good | F83: 1 | G83: 1 | H83: 1 | I83: 1 | J83: Sous-comptage eau rapporté à la GTB | K83: 1. Un compteur d'eau avec sortie à impulsions ou autre protocole ouvert est installé sur toutes les alimentations en eau potable du bâtiment. 2. Les zones du bâtiment ou les installations consommatrices d'eau présentant une demande importante doivent être équipées de sous-compteurs facilement accessibles ou d'un système de surveillance de la consommation d'eau intégré à l'installation ou à la zone. 3. Un système de surveillance de la consommation d'eau adapté à la taille du bâtiment est en place. 3.a. Pour les bâtiments d'une surface intérieure brute ≥ 1 000 m², les compteurs d'eau sont connectés à un système de surveillance et de gestion. 3.b. Pour les bâtiments d'une surface intérieure brute < 1 000 m², les compteurs d'eau sont soit : 3.b.i. Connectés à un système de surveillance et de gestion de l'eau approprié. 3.b.ii. Des compteurs accessibles avec sorties à impulsions ou autres protocoles de communication ouverts. 4. Les personnes responsables du suivi de la consommation d'eau du bâtiment doivent pouvoir identifier clairement les usages de l'eau et les zones couvertes par chaque compteur. | L83: Mise en place d'un compteur sur la principale adduction d'eau. Comptage de chaque espace consommant plus de 10% de l'ensemble de la demande. Les compteurs doivent pouvoir être reliés à une GTB.
A84: Wat 03 | B84: Système de détection des fuites | C84: 1 | D84: APS-APD-PRO-DCE | E84: - | F84: 1 | G84: 0 | H84: 0 | I84: 1 | J84: Détection des fuites | K84: 1. Installer un système de détection de fuites capable de détecter une fuite d'eau importante : 1.a Sur le réseau d'alimentation en eau du bâtiment, afin de détecter toute fuite importante à l'intérieur du bâtiment. ET 1.b Entre le bâtiment et le réseau d'alimentation en eau, afin de détecter toute fuite importante entre le réseau et le bâtiment concerné. | L84: Un système de détection des fuites capable de détecter une fuite importante sur l’approvisionnement en eau principal du bâtiment, à l’intérieur du bâtiment, mais aussi entre le bâtiment et le compteur du fournisseur d’eau, est installé.
A85: Wat 03 | B85: Dispositifs de contrôle des débits (tous les bâtiments sauf les bâtiments résidentiels) | C85: 2 | D85: PRO-DCE | E85: - | F85: 0 | G85: 0 | H85: 0 | I85: 1 | J85: Coupure eau à vérifier | K85: 2. Des dispositifs de contrôle de débit qui régulent l'approvisionnement en eau de chaque zone ou installation WC en fonction de la demande sont installés. | L85: Installation de systèmes coupant l'alimentation en eau potable des blocs sanitaires, hors temps de présence des occupants.
A86: Wat 03 | B86: Isolation des fuites (résidentiel uniquement) | C86: 3-4 | D86: PRO-DCE | E86: - | F86: 0 | G86: 0 | H86: 0 | I86: 0 | K86: 3. Les vannes d'isolement sont placées dans un endroit accessible permettant de couper manuellement l'eau chaude et l'eau froide séparément pour les alimentations suivantes : 3.a Arrivée d'eau du logement 3.b Robinets 3.c Douches 3.d Systèmes de chauffage ou d'eau chaude sanitaire 3.e Appareils électroménagers (ex. : lave-vaisselle, lave-linge, etc.) 4. Les vannes d'isolement doivent être clairement étiquetées.
A87: Wat 04 | B87: Equipements à faible consommation d'eau pour usage autre que sanitaire | C87: 1-4 | D87: APS-APD-PRO-DCE | E87: - | F87: 0 | G87: 0 | H87: 0 | I87: 0 | J87: Vérifier la présence de gros consommateurs d'eau | K87: 1. Identifier les systèmes et équipements qui consomment des quantités importantes d'eau à des fins non sanitaires et qui sont inclus dans le cahier des charges du projet (voir M1). 2. Déterminer le ratio entre la consommation d'eau à des fins non sanitaires et la consommation d'eau sanitaire afin de déterminer le nombre de crédits disponibles (voir tableau 65). 3. Démontrer que les systèmes et équipements installés utilisant de l'eau à des fins non sanitaires sont économes en eau (voir M2). 4. Déterminer le nombre de crédits accordés en fonction du pourcentage des besoins en eau à des fins non sanitaires couverts par des équipements économes en eau (voir tableau 66). | L87: De 1 à 3 crédit selon l'importace des consommations d'eau non sanitaire. Installation de système à faible consommation d'eau pour les consommations d'eau non sanitaires (arrosage, lavage, refroidissement, piscines, autres).
A88: Wat 05 | B88: Estimation de la consommation d'eau du bâtiment | C88: 1 | D88: APS-APD-PRO-DCE | E88: - | F88: 0 | G88: 0 | H88: 0 | I88: 1 | J88: Calcul à réaliser | K88: 1. Estimer la consommation annuelle d'eau opérationnelle (en exploitation) du bâtiment. | L88: Calcul détaillé de la consommation d'eau future
A89: Wat 05X | B89: Annonce d'un objectif de performance en matière de consommation d'eau et engagement à mesurer la consommation d'eau en exploitation | C89: 2-5 | D89: APS-APD-PRO-DCE | E89: - | F89: 0 | G89: 0 | H89: 0 | I89: 1 | J89: objectif à annoncer | K89: 2. Obtenir le crédit pour la prévision de la consommation d'eau opérationnelle. 3. Obtenir le maximum de crédits disponibles pour le suivi de la consommation d'eau (Wat 02). 4. Un objectif de performance sur la consommation d'eau a été communiqué aux parties prenantes et rendu public avant la réception des travaux. 5. Le client ou l'occupant du bâtiment s'engage à financer la mesure et le reporting de la consommation d'eau en service une fois le bâtiment occupé. Cela nécessite la désignation d'une personne ou d'un organisme qualifié pour mesurer et rendre compte de la consommation opérationnelle réelle. | L89: Valider les crédit Wat02 et Wat05. Annoncer un objectif de consommation d'eau aux parties prenantes du projet. Mesurer les consommations d'eau pendant au moins un an après occupation.
A90: Mat 01 | B90: Analyse du cycle de vie - APS | C90: 1-2 | D90: APS | E90: Excellent (APS ou APD-PRO ou fin de chantier), Outstanding | F90: 2 | G90: 0 | H90: 0 | I90: 0 | K90: 1. Réalisez une analyse du cycle de vie (ACV) en phase de conception préliminaire pour les matériaux utilisés dans le bâtiment. L'ACV : 1.a Respecte les exigences relatives aux outils et au périmètre définies dans le critère M1. 1.b Inclut les évaluations des options pertinentes, y compris une évaluation de référence. Il n'est pas nécessaire de réaliser un nombre précis d'évaluations d'options pour le projet. 1.c Sert de base au choix des solutions de conception et des matériaux, dans le but de minimiser l'impact environnemental. Si aucune solution alternative à faible impact environnemental n'a été retenue, ce choix doit être justifié. 2. À partir des résultats de l'ACV en phase de conception préliminaire (critère 1), indiquez les émissions de carbone intrinsèque des matériaux utilisés dans le bâtiment. Les résultats doivent être présentés via la plateforme BREEAM. Pour garantir la cohérence, veuillez suivre les exigences du critère M2. | L90: Le projet fait appel à un outil d'analyse du cycle de vie (ACV) pour orienter les choix de conception en phase de début de conception
A91: Mat 01 | B91: Analyse du cycle de vie - APD-PRO | C91: 3-4 | D91: APD-PRO | E91: Excellent (APS ou APD-PRO ou fin de chantier), Outstanding | F91: 1 | G91: 1 | H91: 1 | I91: 1 | J91: Option ACV MAt01 | K91: 3. Réalisez une analyse du cycle de vie (ACV) en phase de conception technique pour les matériaux utilisés dans le bâtiment. L'ACV doit : 3.a Respecter les exigences relatives aux outils et au périmètre définies dans M1. 3.b Inclure au moins une évaluation illustrant l'évolution de la conception et des spécifications lors de la phase de conception technique. 4. À partir des résultats de l'ACV de conception technique (critère 3), indiquez les émissions de carbone intrinsèque liées aux matériaux utilisés dans le bâtiment. Les résultats doivent être présentés via la plateforme BREEAM. Pour garantir la cohérence, veuillez suivre les exigences de M2. | L91: Le projet fait appel à un outil d'analyse du cycle de vie (ACV) en phase APD ou PRO et analyse les évolutions avec la phase précédente
A92: Mat 01 | B92: Analyse du cycle de vie - fin de chantier | C92: 5-6 | E92: Excellent (APS ou APD-PRO ou fin de chantier), Outstanding | F92: 2 | G92: 2 | H92: 2 | I92: 2 | J92: Option ACV MAt01 | K92: 5. Réaliser une analyse du cycle de vie (ACV) post-construction à partir des matériaux utilisés dans le bâtiment. L'ACV doit : 5.a Respecter les exigences relatives aux outils et au périmètre défini dans le critère M1. 5.b Inclure les spécifications de l'ouvrage réalisé après la construction. 6. À partir des résultats de l'ACV post-construction (critère 5), indiquez les émissions de carbone indirectes liées aux matériaux utilisés dans le bâtiment. Les résultats doivent être présentés via la plateforme BREEAM. Pour garantir la cohérence, veuillez suivre les exigences du critère M2. | L92: Le projet fait appel à un outil d'analyse du cycle de vie (ACV) sur la base des informations de fin de chantier (DOE)
A93: Mat 01 | B93: Performance de l'ACV selon le BRE | C93: 7 | E93: - | F93: 0 | G93: 0 | H93: 0 | I93: 2 | J93: selon benchmark BRE | K93: 7 Pour les types d'évaluation et de bâtiments concernés, comparez les émissions de carbone intrinsèque calculées (modules A1-A5, B1-B5, C1-C4) à la valeur de référence (voir tableau 68). La comparaison avec la référence doit utiliser le calcul de carbone intrinsèque le plus récent disponible : 7.a Pour l'évaluation intermédiaire en phase de conception : 7.a.i Analyse du cycle de vie (ACV) de la conception technique 7.b Pour l'évaluation finale en phase post-construction : 7.b.i Analyse du cycle de vie (ACV) post-construction Classe A, B, C = 2 crédits, classe D, E = 1 crédit | L93: Les données de l'ACV sont reportées par phase de vie du projet (module A1-A5, B1-B5, C1-C4, et D quand disponible). Le niveau carbone du projet est inférieur au seuil du BRE (classe E pour 1 points ou B pour 2 points)
A94: Mat 01X | B94: Performance de l'ACV selon le BRE | C94: 7 | E94: - | F94: 0 | G94: 0 | H94: 0 | I94: 0 | K94: 8 Pour les types d'évaluation et de bâtiments concernés, comparez les émissions de carbone intrinsèque calculées (modules A1-A5, B1-B5, C1-C4) à la valeur de référence (voir tableau 68). La comparaison avec la référence doit utiliser le calcul de carbone intrinsèque le plus récent disponible : 7.a Pour l'évaluation intermédiaire en phase de conception : 7.a.i Analyse du cycle de vie (ACV) de la conception technique 7.b Pour l'évaluation finale en phase post-construction : 7.b.i Analyse du cycle de vie (ACV) post-construction Classe A = 1 crédit exemplaire supplémentaire | L94: Le niveau carbone du projet est en classe A selon les seuils du BRE.
A95: Mat 01X | B95: ACV vérifiée par un tiers | C95: 8-9 | E95: - | F95: 1 | G95: 0 | H95: 0 | I95: 1 | J95: non visé (possible) | K95: 8. Un tiers dûment qualifié vérifie l'analyse du cycle de vie (ACV) du bâtiment. Ce tiers doit : 8.a. Produire un rapport décrivant comment il a vérifié que l'ACV du bâtiment représente fidèlement les conceptions envisagées lors des phases suivantes : 8.a.i. de conception préliminaire, 8.a.ii. de conception technique, et 8.a.iii. de post-construction (uniquement pertinent si les critères 5 et 6 ont été ciblés). 8.b. Détailler dans le rapport les vérifications effectuées pour chaque option d'ACV. Ces vérifications doivent au minimum inclure les exigences de qualité présentées dans le tableau 69 du document M3. 8.c. Inclure dans le rapport le détail de ses compétences et de son expérience pertinentes, ainsi qu'une déclaration attestant de son indépendance vis-à-vis du client et de l'équipe de conception. 9. Toute recommandation formulée dans le rapport de vérification par un tiers doit être mise en œuvre et justifiée. | L95: Faire vérifier l'ACV à chaque phase du projet par un tiers (APS / PRO / fin de chantier)
A96: Mat 01X | B96: Publication de l'ACV à chaque phase | C96: 10 | E96: - | F96: 1 | G96: 0 | H96: 0 | I96: 1 | J96: possible si choix client | K96: 10 Pour chaque phase de projet ayant fait l’objet d’une ACV, soumettez les résultats et les données d’ACV ou de carbone à une base de données d’ACV ou de carbone publique pertinente. Si aucune option locale ou nationale appropriée n’est disponible, soumettez les données à la base de données carbone du secteur bâti (BECD). | L96: Rendre public les résultats des ACV à chaque phase.
A97: Mat 02 | B97: Déclarations environnementales produit | C97: 1-3 | E97: - | F97: 1 | G97: 0 | H97: 0 | I97: 1 | J97: Récupération des FDES de l'ensemble des produits | K97: 1. Spécifiez les produits de construction dotés de déclarations environnementales de produit (DEP) atteignant un score total d'au moins 20 points DEP, conformément à la méthode M1. 2. Saisissez les détails de chaque DEP sur la plateforme BREEAM, y compris la classification de la catégorie de matériau. Le score DEP et le nombre de crédits obtenus seront calculés automatiquement. | L97: Prescrire des produits couverts par de la données environnementale individuelle ou collective, pour 20 points. 4 points maximum par type de matériau (Bois, béton, pierre, métal, …) (Cela représente au moins 40 produits en FDES collective).
A98: Mat 03 | B98: Prérequis | C98: 1 | D98: PRO-DCE-VISA-DET | E98: Pass | F98: 0 | G98: 0 | H98: 0 | I98: 0 | J98: Ok, pré-requis Man 03 | K98: 1. Tout le bois et les produits dérivés du bois utilisés dans le cadre de ce projet provient du bois récolté et commercialisé légalement. | L98: L’intégralité du bois d’œuvre et des produits utilisant du bois employés au cours du processus de construction du projet est du « bois d’œuvre abattu et commercialisé légalement »
A99: Mat 03 | B99: Plan d’approvisionnement durable | C99: 2 | D99: APS-APD-VISA-DET | E99: - | F99: 1 | G99: 0 | H99: 1 | I99: 0 | J99: option Mat03 | K99: 2. Un plan d'approvisionnement durable doit être utilisé par l'équipe de conception pour orienter les spécifications vers des produits de construction durables. Ce plan doit : 2.a Être en place avant la fin de la conception préliminaire. 2.b Inclure des objectifs, des cibles et des cibles stratégiques de durabilité pour orienter les activités d'approvisionnement. L'atteinte des cibles n'est pas nécessaire pour l'octroi de crédits après la construction, mais une justification doit être fournie pour les cibles non atteintes. 2.c Inclure une exigence d'évaluation du potentiel d'approvisionnement local en produits de construction. Une politique d'approvisionnement local en produits de construction, dans la mesure du possible, doit être mise en place. 2.d Inclure le détail des procédures en place pour vérifier la mise en œuvre effective du plan d'approvisionnement durable. 2.e La politique et les procédures documentées doivent être diffusées à tout le personnel interne et externe concerné et intégrées au contrat de construction afin d'en garantir l'applicabilité au projet évalué. En outre, si le plan est appliqué à plusieurs sites ou adopté au niveau organisationnel, il doit : 2.f Identifier les risques et les opportunités liés aux achats au regard d’un large éventail de questions sociales, environnementales et économiques en suivant le processus défini dans la norme ISO 20400:2017. | L99: le client ou le promoteur dispose d’une politique ou d’une procédure documentée qui définit les exigences d’approvisionnement pour la totalité des fournisseurs et les filières à respecter pour un approvisionnement responsable des matériaux de construction.
A100: Mat 03 | B100: Mesurer l’approvisionnement responsable | C100: 3 | D100: APS-APD-VISA-DET | E100: - | F100: 3 | G100: 0 | H100: 0 | I100: 0 | K100: 3 Sur la plateforme BREEAM, utilisez le calculateur Mat 03 et suivez les instructions M1 pour déterminer le nombre de crédits obtenus pour les produits de construction. Les crédits sont attribués proportionnellement à l'étendue de l'évaluation (voir M2) et au nombre de points obtenus, comme indiqué dans le tableau 72. 10% = 1 crédit, 20% = 2 crédits, 30% = 3 crédits | L100: Les points s'obtiennent en mettant en œuvre une politique d'achat de matériaux responsables (dont la filière de production et de distribution est certifiée) pour le projet. (3 niveaux possibles suivant si 10%, 20% ou 30% des points disponibles ont été obtenus)
...

Sheet Score
C1: Applicable | D1: Scénario 1 | E1: Scénario 2 | F1: Scénario 3 | G1: Applicable | H1: Scénario 1 | I1: Scénario 2 | J1: Scénario 3 | K1: % par crédit | L1: Scénario 1 | M1: Scénario 2 | N1: Scénario 3 | P1: Pondération BREEAM Project | Q1: Fully Fitted | R1: =SUM(R3:R12) -> 0.47196032 | S1: =SUM(S3:S12) -> 0.60985317 | T1: =SUM(T3:T12) -> 1.7495198 | U1: =SUM(U3:U12) -> 1.085 | Z1: Non residential weighting France
A2: Management | B2: Man 01 | C2: =SUMIFS(Evaluation!$F$2:$F$142,Evaluation!$A$2:$A$142,$B2&"*",Evaluation!$A$2:$A$142,"<>*X*") -> 4 | D2: =SUMIFS(Evaluation!$G$2:$G$142,Evaluation!$A$2:$A$142,$B2&"*",Evaluation!$A$2:$A$142,"<>*X*") -> 3 | E2: =SUMIFS(Evaluation!$H$2:$H$142,Evaluation!$A$2:$A$142,$B2&"*",Evaluation!$A$2:$A$142,"<>*X*") -> 3 | F2: =SUMIFS(Evaluation!$I$2:$I$142,Evaluation!$A$2:$A$142,$B2&"*",Evaluation!$A$2:$A$142,"<>*X*") -> 3 | G2: =SUM(C2:C6) -> 15 | H2: =SUM(D2:D6) -> 8 | I2: =SUM(E2:E6) -> 11 | J2: =SUM(F2:F6) -> 18 | K2: =Q3/G2 -> 0.0073333333 | L2: =H2*K2 -> 0.058666667 | M2: =I2*K2 -> 0.080666667 | N2: =J2*K2 -> 0.132 | P2: Thème | Q2: Pondération | R2: Scénario 1 | S2: Scénario 2 | T2: Scénario 3 | U2: Maximum | V2: Scénario 1 | W2: Scénario 2 | X2: Scénario 3 | Z2: Fully Fitted | AA2: Shell only | AB2: Shell and core
B3: Man 02 | C3: =SUMIFS(Evaluation!$F$2:$F$142,Evaluation!$A$2:$A$142,$B3&"*",Evaluation!$A$2:$A$142,"<>*X*") -> 4 | D3: =SUMIFS(Evaluation!$G$2:$G$142,Evaluation!$A$2:$A$142,$B3&"*",Evaluation!$A$2:$A$142,"<>*X*") -> 1 | E3: =SUMIFS(Evaluation!$H$2:$H$142,Evaluation!$A$2:$A$142,$B3&"*",Evaluation!$A$2:$A$142,"<>*X*") -> 4 | F3: =SUMIFS(Evaluation!$I$2:$I$142,Evaluation!$A$2:$A$142,$B3&"*",Evaluation!$A$2:$A$142,"<>*X*") -> 3 | P3: =$A$2 -> Management | Q3: =IF($Q$1=$Z$2,Z3,IF($Q$1=$AA$2,AA3,AB3)) -> 0.11 | R3: =L2 -> 0.058666667 | S3: =M2 -> 0.080666667 | T3: =N2 -> 0.132 | U3: =Q3 -> 0.11 | V3: =R3/$U3 -> 0.53333333 | W3: =S3/$U3 -> 0.73333333 | X3: =T3/$U3 -> 1.2 | Z3: 0.11 | AA3: 0.1243 | AB3: 0.1048
B4: Man 03 | C4: =SUMIFS(Evaluation!$F$2:$F$142,Evaluation!$A$2:$A$142,$B4&"*",Evaluation!$A$2:$A$142,"<>*X*") -> 6 | D4: =SUMIFS(Evaluation!$G$2:$G$142,Evaluation!$A$2:$A$142,$B4&"*",Evaluation!$A$2:$A$142,"<>*X*") -> 4 | E4: =SUMIFS(Evaluation!$H$2:$H$142,Evaluation!$A$2:$A$142,$B4&"*",Evaluation!$A$2:$A$142,"<>*X*") -> 4 | F4: =SUMIFS(Evaluation!$I$2:$I$142,Evaluation!$A$2:$A$142,$B4&"*",Evaluation!$A$2:$A$142,"<>*X*") -> 6 | P4: =$A$7 -> Health and Wellbeing | Q4: =IF($Q$1=$Z$2,Z4,IF($Q$1=$AA$2,AA4,AB4)) -> 0.19 | R4: =L7 -> 0.078333333 | S4: =M7 -> 0.11 | T4: =N7 -> 0.52166667 | U4: =Q4 -> 0.19 | V4: =R4/$U4 -> 0.4122807 | W4: =S4/$U4 -> 0.57894737 | X4: =T4/$U4 -> 2.745614 | Z4: 0.19 | AA4: 0.1093 | AB4: 0.1248
B5: Man 04 | C5: =SUMIFS(Evaluation!$F$2:$F$142,Evaluation!$A$2:$A$142,$B5&"*",Evaluation!$A$2:$A$142,"<>*X*") -> 1 | D5: =SUMIFS(Evaluation!$G$2:$G$142,Evaluation!$A$2:$A$142,$B5&"*",Evaluation!$A$2:$A$142,"<>*X*") -> 0 | E5: =SUMIFS(Evaluation!$H$2:$H$142,Evaluation!$A$2:$A$142,$B5&"*",Evaluation!$A$2:$A$142,"<>*X*") -> 0 | F5: =SUMIFS(Evaluation!$I$2:$I$142,Evaluation!$A$2:$A$142,$B5&"*",Evaluation!$A$2:$A$142,"<>*X*") -> 4 | P5: =$A$17 -> Energy | Q5: =IF($Q$1=$Z$2,Z5,IF($Q$1=$AA$2,AA5,AB5)) -> 0.16 | R5: =L17 -> 0.068571429 | S5: =M17 -> 0.12571429 | T5: =N17 -> 0.36571429 | U5: =Q5 -> 0.16 | V5: =R5/$U5 -> 0.42857143 | W5: =S5/$U5 -> 0.78571429 | X5: =T5/$U5 -> 2.2857143 | Z5: 0.16 | AA5: 0.0787 | AB5: 0.1779
B6: Man 05 | C6: =SUMIFS(Evaluation!$F$2:$F$142,Evaluation!$A$2:$A$142,$B6&"*",Evaluation!$A$2:$A$142,"<>*X*") -> 0 | D6: =SUMIFS(Evaluation!$G$2:$G$142,Evaluation!$A$2:$A$142,$B6&"*",Evaluation!$A$2:$A$142,"<>*X*") -> 0 | E6: =SUMIFS(Evaluation!$H$2:$H$142,Evaluation!$A$2:$A$142,$B6&"*",Evaluation!$A$2:$A$142,"<>*X*") -> 0 | F6: =SUMIFS(Evaluation!$I$2:$I$142,Evaluation!$A$2:$A$142,$B6&"*",Evaluation!$A$2:$A$142,"<>*X*") -> 2 | P6: =$A$25 -> Transport | Q6: =IF($Q$1=$Z$2,Z6,IF($Q$1=$AA$2,AA6,AB6)) -> 0.08 | R6: =L25 -> 0.033333333 | S6: =M25 -> 0.04 | T6: =N25 -> 0.066666667 | U6: =Q6 -> 0.08 | V6: =R6/$U6 -> 0.41666667 | W6: =S6/$U6 -> 0.5 | X6: =T6/$U6 -> 0.83333333 | Z6: 0.08 | AA6: 0.1265 | AB6: 0.0889
A7: Health and Wellbeing | B7: Hea 01 | C7: =SUMIFS(Evaluation!$F$2:$F$142,Evaluation!$A$2:$A$142,$B7&"*",Evaluation!$A$2:$A$142,"<>*X*") -> 2 | D7: =SUMIFS(Evaluation!$G$2:$G$142,Evaluation!$A$2:$A$142,$B7&"*",Evaluation!$A$2:$A$142,"<>*X*") -> 1 | E7: =SUMIFS(Evaluation!$H$2:$H$142,Evaluation!$A$2:$A$142,$B7&"*",Evaluation!$A$2:$A$142,"<>*X*") -> 2 | F7: =SUMIFS(Evaluation!$I$2:$I$142,Evaluation!$A$2:$A$142,$B7&"*",Evaluation!$A$2:$A$142,"<>*X*") -> 1 | G7: =SUM(C7:C16)-C15 -> 6 | H7: =SUM(D7:D16)-D15 -> 2 | I7: =SUM(E7:E16)-E15 -> 3 | J7: =SUM(F7:F16)-F15 -> 16 | K7: =Q4/G7 -> 0.031666667 | L7: =H7*$K$7+D15*$Q$13 -> 0.078333333 | M7: =I7*$K$7+E15*$Q$13 -> 0.11 | N7: =J7*$K$7+F15*$Q$13 -> 0.52166667 | P7: =$A$27 -> Water | Q7: =IF($Q$1=$Z$2,Z7,IF($Q$1=$AA$2,AA7,AB7)) -> 0.075 | R7: =L27 -> 0.0375 | S7: =M27 -> 0.0375 | T7: =N27 -> 0.3 | U7: =Q7 -> 0.075 | V7: =R7/$U7 -> 0.5 | W7: =S7/$U7 -> 0.5 | X7: =T7/$U7 -> 4 | Z7: 0.075 | AA7: 0.0324 | AB7: 0.0834
B8: Hea 02 | C8: =SUMIFS(Evaluation!$F$2:$F$142,Evaluation!$A$2:$A$142,$B8&"*",Evaluation!$A$2:$A$142,"<>*X*") -> 1 | D8: =SUMIFS(Evaluation!$G$2:$G$142,Evaluation!$A$2:$A$142,$B8&"*",Evaluation!$A$2:$A$142,"<>*X*") -> 1 | E8: =SUMIFS(Evaluation!$H$2:$H$142,Evaluation!$A$2:$A$142,$B8&"*",Evaluation!$A$2:$A$142,"<>*X*") -> 1 | F8: =SUMIFS(Evaluation!$I$2:$I$142,Evaluation!$A$2:$A$142,$B8&"*",Evaluation!$A$2:$A$142,"<>*X*") -> 2 | P8: =$A$32 -> Materials | Q8: =IF($Q$1=$Z$2,Z8,IF($Q$1=$AA$2,AA8,AB8)) -> 0.155 | R8: =L32 -> 0.051666667 | S8: =M32 -> 0.064583333 | T8: =N32 -> 0.090416667 | U8: =Q8 -> 0.155 | V8: =R8/$U8 -> 0.33333333 | W8: =S8/$U8 -> 0.41666667 | X8: =T8/$U8 -> 0.58333333 | Z8: 0.155 | AA8: 0.2101 | AB8: 0.1723
B9: Hea 03 | C9: =SUMIFS(Evaluation!$F$2:$F$142,Evaluation!$A$2:$A$142,$B9&"*",Evaluation!$A$2:$A$142,"<>*X*") -> 0 | D9: =SUMIFS(Evaluation!$G$2:$G$142,Evaluation!$A$2:$A$142,$B9&"*",Evaluation!$A$2:$A$142,"<>*X*") -> 0 | E9: =SUMIFS(Evaluation!$H$2:$H$142,Evaluation!$A$2:$A$142,$B9&"*",Evaluation!$A$2:$A$142,"<>*X*") -> 0 | F9: =SUMIFS(Evaluation!$I$2:$I$142,Evaluation!$A$2:$A$142,$B9&"*",Evaluation!$A$2:$A$142,"<>*X*") -> 0 | P9: =$A$37 -> Waste | Q9: =IF($Q$1=$Z$2,Z9,IF($Q$1=$AA$2,AA9,AB9)) -> 0.07 | R9: =L37 -> 0.038888889 | S9: =M37 -> 0.038888889 | T9: =N37 -> 0.038888889 | U9: =Q9 -> 0.07 | V9: =R9/$U9 -> 0.55555556 | W9: =S9/$U9 -> 0.55555556 | X9: =T9/$U9 -> 0.55555556 | Z9: 0.07 | AA9: 0.0996 | AB9: 0.07
B10: Hea 04 | C10: =SUMIFS(Evaluation!$F$2:$F$142,Evaluation!$A$2:$A$142,$B10&"*",Evaluation!$A$2:$A$142,"<>*X*") -> 0 | D10: =SUMIFS(Evaluation!$G$2:$G$142,Evaluation!$A$2:$A$142,$B10&"*",Evaluation!$A$2:$A$142,"<>*X*") -> 0 | E10: =SUMIFS(Evaluation!$H$2:$H$142,Evaluation!$A$2:$A$142,$B10&"*",Evaluation!$A$2:$A$142,"<>*X*") -> 0 | F10: =SUMIFS(Evaluation!$I$2:$I$142,Evaluation!$A$2:$A$142,$B10&"*",Evaluation!$A$2:$A$142,"<>*X*") -> 4 | P10: =$A$43 -> Land Use and ecology | Q10: =IF($Q$1=$Z$2,Z10,IF($Q$1=$AA$2,AA10,AB10)) -> 0.105 | R10: =L43 -> 0.075 | S10: =M43 -> 0.0825 | T10: =N43 -> 0.0675 | U10: =Q10 -> 0.105 | V10: =R10/$U10 -> 0.71428571 | W10: =S10/$U10 -> 0.78571429 | X10: =T10/$U10 -> 0.64285714 | Z10: 0.105 | AA10: 0.1661 | AB10: 0.1167
B11: Hea 05 | C11: =SUMIFS(Evaluation!$F$2:$F$142,Evaluation!$A$2:$A$142,$B11&"*",Evaluation!$A$2:$A$142,"<>*X*") -> 0 | D11: =SUMIFS(Evaluation!$G$2:$G$142,Evaluation!$A$2:$A$142,$B11&"*",Evaluation!$A$2:$A$142,"<>*X*") -> 0 | E11: =SUMIFS(Evaluation!$H$2:$H$142,Evaluation!$A$2:$A$142,$B11&"*",Evaluation!$A$2:$A$142,"<>*X*") -> 0 | F11: =SUMIFS(Evaluation!$I$2:$I$142,Evaluation!$A$2:$A$142,$B11&"*",Evaluation!$A$2:$A$142,"<>*X*") -> 3 | P11: =$A$48 -> Pollution | Q11: =IF($Q$1=$Z$2,Z11,IF($Q$1=$AA$2,AA11,AB11)) -> 0.04 | R11: =L48 -> 0.02 | S11: =M48 -> 0.02 | T11: =N48 -> 0.066666667 | U11: =Q11 -> 0.04 | V11: =R11/$U11 -> 0.5 | W11: =S11/$U11 -> 0.5 | X11: =T11/$U11 -> 1.6666667 | Z11: 0.04 | AA11: 0.0292 | AB11: 0.0445
B12: Hea 06 | C12: =SUMIFS(Evaluation!$F$2:$F$142,Evaluation!$A$2:$A$142,$B12&"*",Evaluation!$A$2:$A$142,"<>*X*") -> 1 | D12: =SUMIFS(Evaluation!$G$2:$G$142,Evaluation!$A$2:$A$142,$B12&"*",Evaluation!$A$2:$A$142,"<>*X*") -> 0 | E12: =SUMIFS(Evaluation!$H$2:$H$142,Evaluation!$A$2:$A$142,$B12&"*",Evaluation!$A$2:$A$142,"<>*X*") -> 0 | F12: =SUMIFS(Evaluation!$I$2:$I$142,Evaluation!$A$2:$A$142,$B12&"*",Evaluation!$A$2:$A$142,"<>*X*") -> 3 | P12: =$A$53 -> Innovation | Q12: =IF($Q$1=$Z$2,Z12,IF($Q$1=$AA$2,AA12,AB12)) -> 0.1 | R12: =MIN(L53,0.1) -> 0.01 | S12: =MIN(M53,0.1) -> 0.01 | T12: =MIN(N53,0.1) -> 0.1 | U12: =Q12 -> 0.1 | V12: =R12/$U12 -> 0.1 | W12: =S12/$U12 -> 0.1 | X12: =T12/$U12 -> 1 | Z12: 0.1 | AA12: 0.1 | AB12: 0.1
B13: Hea 07 | C13: =SUMIFS(Evaluation!$F$2:$F$142,Evaluation!$A$2:$A$142,$B13&"*",Evaluation!$A$2:$A$142,"<>*X*") -> 2 | D13: =SUMIFS(Evaluation!$G$2:$G$142,Evaluation!$A$2:$A$142,$B13&"*",Evaluation!$A$2:$A$142,"<>*X*") -> 0 | E13: =SUMIFS(Evaluation!$H$2:$H$142,Evaluation!$A$2:$A$142,$B13&"*",Evaluation!$A$2:$A$142,"<>*X*") -> 0 | F13: =SUMIFS(Evaluation!$I$2:$I$142,Evaluation!$A$2:$A$142,$B13&"*",Evaluation!$A$2:$A$142,"<>*X*") -> 2 | P13: Hazards | Q13: =IF($Q$1=$Z$2,Z13,IF($Q$1=$AA$2,AA13,AB13)) -> 0.015 | Z13: 0.015 | AA13: 0.0237 | AB13: 0.0167
B14: Hea 09 | C14: =SUMIFS(Evaluation!$F$2:$F$142,Evaluation!$A$2:$A$142,$B14&"*",Evaluation!$A$2:$A$142,"<>*X*") -> 0 | D14: =SUMIFS(Evaluation!$G$2:$G$142,Evaluation!$A$2:$A$142,$B14&"*",Evaluation!$A$2:$A$142,"<>*X*") -> 0 | E14: =SUMIFS(Evaluation!$H$2:$H$142,Evaluation!$A$2:$A$142,$B14&"*",Evaluation!$A$2:$A$142,"<>*X*") -> 0 | F14: =SUMIFS(Evaluation!$I$2:$I$142,Evaluation!$A$2:$A$142,$B14&"*",Evaluation!$A$2:$A$142,"<>*X*") -> 0 | P14: Score BREEAM | R14: =SUM(R3:R12) -> 0.47196032 | S14: =SUM(S3:S12) -> 0.60985317 | T14: =SUM(T3:T12) -> 1.7495198
B15: Hea 10 | C15: =SUMIFS(Evaluation!$F$2:$F$142,Evaluation!$A$2:$A$142,$B15&"*",Evaluation!$A$2:$A$142,"<>*X*") -> 1 | D15: =SUMIFS(Evaluation!$G$2:$G$142,Evaluation!$A$2:$A$142,$B15&"*",Evaluation!$A$2:$A$142,"<>*X*") -> 1 | E15: =SUMIFS(Evaluation!$H$2:$H$142,Evaluation!$A$2:$A$142,$B15&"*",Evaluation!$A$2:$A$142,"<>*X*") -> 1 | F15: =SUMIFS(Evaluation!$I$2:$I$142,Evaluation!$A$2:$A$142,$B15&"*",Evaluation!$A$2:$A$142,"<>*X*") -> 1 | R15: =IF(R14<0.3,"UNCLASSIFIED",IF(R14<0.45,"PASS",IF(R14<0.55,"GOOD",IF(R14<0.7,"VERY GOOD",IF(R14<0.85,"EXCELLENT","OUTSTANDING"))))) -> GOOD | S15: =IF(S14<0.3,"UNCLASSIFIED",IF(S14<0.45,"PASS",IF(S14<0.55,"GOOD",IF(S14<0.7,"VERY GOOD",IF(S14<0.85,"EXCELLENT","OUTSTANDING"))))) -> VERY GOOD | T15: =IF(T14<0.3,"UNCLASSIFIED",IF(T14<0.45,"PASS",IF(T14<0.55,"GOOD",IF(T14<0.7,"VERY GOOD",IF(T14<0.85,"EXCELLENT","OUTSTANDING"))))) -> OUTSTANDING
B16: Hea 11 | C16: =SUMIFS(Evaluation!$F$2:$F$142,Evaluation!$A$2:$A$142,$B16&"*",Evaluation!$A$2:$A$142,"<>*X*") -> 0 | D16: =SUMIFS(Evaluation!$G$2:$G$142,Evaluation!$A$2:$A$142,$B16&"*",Evaluation!$A$2:$A$142,"<>*X*") -> 0 | E16: =SUMIFS(Evaluation!$H$2:$H$142,Evaluation!$A$2:$A$142,$B16&"*",Evaluation!$A$2:$A$142,"<>*X*") -> 0 | F16: =SUMIFS(Evaluation!$I$2:$I$142,Evaluation!$A$2:$A$142,$B16&"*",Evaluation!$A$2:$A$142,"<>*X*") -> 1
A17: Energy | B17: Ene 01 | C17: =SUMIFS(Evaluation!$F$2:$F$142,Evaluation!$A$2:$A$142,$B17&"*",Evaluation!$A$2:$A$142,"<>*X*") -> 9 | D17: =SUMIFS(Evaluation!$G$2:$G$142,Evaluation!$A$2:$A$142,$B17&"*",Evaluation!$A$2:$A$142,"<>*X*") -> 4 | E17: =SUMIFS(Evaluation!$H$2:$H$142,Evaluation!$A$2:$A$142,$B17&"*",Evaluation!$A$2:$A$142,"<>*X*") -> 6 | F17: =SUMIFS(Evaluation!$I$2:$I$142,Evaluation!$A$2:$A$142,$B17&"*",Evaluation!$A$2:$A$142,"<>*X*") -> 8 | G17: =SUM(C17:C24) -> 14 | H17: =SUM(D17:D24) -> 6 | I17: =SUM(E17:E24) -> 11 | J17: =SUM(F17:F24) -> 32 | K17: =Q5/G17 -> 0.011428571 | L17: =H17*K17 -> 0.068571429 | M17: =I17*K17 -> 0.12571429 | N17: =J17*K17 -> 0.36571429 | Q17: <-Pass-> | R17: 0.2 | S17: 0.2 | T17: 0.3 | U17: 0.2
B18: Ene 02 | C18: =SUMIFS(Evaluation!$F$2:$F$142,Evaluation!$A$2:$A$142,$B18&"*",Evaluation!$A$2:$A$142,"<>*X*") -> 0 | D18: =SUMIFS(Evaluation!$G$2:$G$142,Evaluation!$A$2:$A$142,$B18&"*",Evaluation!$A$2:$A$142,"<>*X*") -> 0 | E18: =SUMIFS(Evaluation!$H$2:$H$142,Evaluation!$A$2:$A$142,$B18&"*",Evaluation!$A$2:$A$142,"<>*X*") -> 0 | F18: =SUMIFS(Evaluation!$I$2:$I$142,Evaluation!$A$2:$A$142,$B18&"*",Evaluation!$A$2:$A$142,"<>*X*") -> 10 | Q18: <-Pass-> | R18: 0.2 | S18: 0.2 | T18: 0.3 | U18: 0.2
B19: Ene 03 | C19: =SUMIFS(Evaluation!$F$2:$F$142,Evaluation!$A$2:$A$142,$B19&"*",Evaluation!$A$2:$A$142,"<>*X*") -> 0 | D19: =SUMIFS(Evaluation!$G$2:$G$142,Evaluation!$A$2:$A$142,$B19&"*",Evaluation!$A$2:$A$142,"<>*X*") -> 0 | E19: =SUMIFS(Evaluation!$H$2:$H$142,Evaluation!$A$2:$A$142,$B19&"*",Evaluation!$A$2:$A$142,"<>*X*") -> 0 | F19: =SUMIFS(Evaluation!$I$2:$I$142,Evaluation!$A$2:$A$142,$B19&"*",Evaluation!$A$2:$A$142,"<>*X*") -> 2 | Q19: <-Good-> | R19: 0.4 | S19: 0.4 | T19: 0.4 | U19: 0.4
B20: Ene 04 | C20: =SUMIFS(Evaluation!$F$2:$F$142,Evaluation!$A$2:$A$142,$B20&"*",Evaluation!$A$2:$A$142,"<>*X*") -> 5 | D20: =SUMIFS(Evaluation!$G$2:$G$142,Evaluation!$A$2:$A$142,$B20&"*",Evaluation!$A$2:$A$142,"<>*X*") -> 2 | E20: =SUMIFS(Evaluation!$H$2:$H$142,Evaluation!$A$2:$A$142,$B20&"*",Evaluation!$A$2:$A$142,"<>*X*") -> 5 | F20: =SUMIFS(Evaluation!$I$2:$I$142,Evaluation!$A$2:$A$142,$B20&"*",Evaluation!$A$2:$A$142,"<>*X*") -> 3 | Q20: <-Very Good-> | R20: 0.55 | S20: 0.55 | T20: 0.55 | U20: 0.55
B21: Ene 05 | C21: =SUMIFS(Evaluation!$F$2:$F$142,Evaluation!$A$2:$A$142,$B21&"*",Evaluation!$A$2:$A$142,"<>*X*") -> 0 | D21: =SUMIFS(Evaluation!$G$2:$G$142,Evaluation!$A$2:$A$142,$B21&"*",Evaluation!$A$2:$A$142,"<>*X*") -> 0 | E21: =SUMIFS(Evaluation!$H$2:$H$142,Evaluation!$A$2:$A$142,$B21&"*",Evaluation!$A$2:$A$142,"<>*X*") -> 0 | F21: =SUMIFS(Evaluation!$I$2:$I$142,Evaluation!$A$2:$A$142,$B21&"*",Evaluation!$A$2:$A$142,"<>*X*") -> 3 | Q21: <-Excellent-> | R21: 0.7 | S21: 0.7 | T21: 0.7 | U21: 0.7
B22: Ene 06 | C22: =SUMIFS(Evaluation!$F$2:$F$142,Evaluation!$A$2:$A$142,$B22&"*",Evaluation!$A$2:$A$142,"<>*X*") -> 0 | D22: =SUMIFS(Evaluation!$G$2:$G$142,Evaluation!$A$2:$A$142,$B22&"*",Evaluation!$A$2:$A$142,"<>*X*") -> 0 | E22: =SUMIFS(Evaluation!$H$2:$H$142,Evaluation!$A$2:$A$142,$B22&"*",Evaluation!$A$2:$A$142,"<>*X*") -> 0 | F22: =SUMIFS(Evaluation!$I$2:$I$142,Evaluation!$A$2:$A$142,$B22&"*",Evaluation!$A$2:$A$142,"<>*X*") -> 5 | Q22: <-Outstanding-> | R22: 0.85 | S22: 0.85 | T22: 0.85 | U22: 0.85
B23: Ene 07 | C23: =SUMIFS(Evaluation!$F$2:$F$142,Evaluation!$A$2:$A$142,$B23&"*",Evaluation!$A$2:$A$142,"<>*X*") -> 0 | D23: =SUMIFS(Evaluation!$G$2:$G$142,Evaluation!$A$2:$A$142,$B23&"*",Evaluation!$A$2:$A$142,"<>*X*") -> 0 | E23: =SUMIFS(Evaluation!$H$2:$H$142,Evaluation!$A$2:$A$142,$B23&"*",Evaluation!$A$2:$A$142,"<>*X*") -> 0 | F23: =SUMIFS(Evaluation!$I$2:$I$142,Evaluation!$A$2:$A$142,$B23&"*",Evaluation!$A$2:$A$142,"<>*X*") -> 0
B24: Ene 08 | C24: =SUMIFS(Evaluation!$F$2:$F$142,Evaluation!$A$2:$A$142,$B24&"*",Evaluation!$A$2:$A$142,"<>*X*") -> 0 | D24: =SUMIFS(Evaluation!$G$2:$G$142,Evaluation!$A$2:$A$142,$B24&"*",Evaluation!$A$2:$A$142,"<>*X*") -> 0 | E24: =SUMIFS(Evaluation!$H$2:$H$142,Evaluation!$A$2:$A$142,$B24&"*",Evaluation!$A$2:$A$142,"<>*X*") -> 0 | F24: =SUMIFS(Evaluation!$I$2:$I$142,Evaluation!$A$2:$A$142,$B24&"*",Evaluation!$A$2:$A$142,"<>*X*") -> 1
A25: Transport | B25: Tra 01 | C25: =SUMIFS(Evaluation!$F$2:$F$142,Evaluation!$A$2:$A$142,$B25&"*",Evaluation!$A$2:$A$142,"<>*X*") -> 2 | D25: =SUMIFS(Evaluation!$G$2:$G$142,Evaluation!$A$2:$A$142,$B25&"*",Evaluation!$A$2:$A$142,"<>*X*") -> 2 | E25: =SUMIFS(Evaluation!$H$2:$H$142,Evaluation!$A$2:$A$142,$B25&"*",Evaluation!$A$2:$A$142,"<>*X*") -> 2 | F25: =SUMIFS(Evaluation!$I$2:$I$142,Evaluation!$A$2:$A$142,$B25&"*",Evaluation!$A$2:$A$142,"<>*X*") -> 2 | G25: =SUM(C25:C26) -> 12 | H25: =SUM(D25:D26) -> 5 | I25: =SUM(E25:E26) -> 6 | J25: =SUM(F25:F26) -> 10 | K25: =Q6/G25 -> 0.0066666667 | L25: =H25*K25 -> 0.033333333 | M25: =I25*K25 -> 0.04 | N25: =J25*K25 -> 0.066666667
B26: Tra 02 | C26: =SUMIFS(Evaluation!$F$2:$F$142,Evaluation!$A$2:$A$142,$B26&"*",Evaluation!$A$2:$A$142,"<>*X*") -> 10 | D26: =SUMIFS(Evaluation!$G$2:$G$142,Evaluation!$A$2:$A$142,$B26&"*",Evaluation!$A$2:$A$142,"<>*X*") -> 3 | E26: =SUMIFS(Evaluation!$H$2:$H$142,Evaluation!$A$2:$A$142,$B26&"*",Evaluation!$A$2:$A$142,"<>*X*") -> 4 | F26: =SUMIFS(Evaluation!$I$2:$I$142,Evaluation!$A$2:$A$142,$B26&"*",Evaluation!$A$2:$A$142,"<>*X*") -> 8
A27: Water | B27: Wat 01 | C27: =SUMIFS(Evaluation!$F$2:$F$142,Evaluation!$A$2:$A$142,$B27&"*",Evaluation!$A$2:$A$142,"<>*X*") -> 0 | D27: =SUMIFS(Evaluation!$G$2:$G$142,Evaluation!$A$2:$A$142,$B27&"*",Evaluation!$A$2:$A$142,"<>*X*") -> 0 | E27: =SUMIFS(Evaluation!$H$2:$H$142,Evaluation!$A$2:$A$142,$B27&"*",Evaluation!$A$2:$A$142,"<>*X*") -> 0 | F27: =SUMIFS(Evaluation!$I$2:$I$142,Evaluation!$A$2:$A$142,$B27&"*",Evaluation!$A$2:$A$142,"<>*X*") -> 4 | G27: =SUM(C27:C31) -> 2 | H27: =SUM(D27:D31) -> 1 | I27: =SUM(E27:E31) -> 1 | J27: =SUM(F27:F31) -> 8 | K27: =IF(G27=0,0,Q7/G27) -> 0.0375 | L27: =H27*K27 -> 0.0375 | M27: =I27*K27 -> 0.0375 | N27: =J27*K27 -> 0.3
B28: Wat 02 | C28: =SUMIFS(Evaluation!$F$2:$F$142,Evaluation!$A$2:$A$142,$B28&"*",Evaluation!$A$2:$A$142,"<>*X*") -> 1 | D28: =SUMIFS(Evaluation!$G$2:$G$142,Evaluation!$A$2:$A$142,$B28&"*",Evaluation!$A$2:$A$142,"<>*X*") -> 1 | E28: =SUMIFS(Evaluation!$H$2:$H$142,Evaluation!$A$2:$A$142,$B28&"*",Evaluation!$A$2:$A$142,"<>*X*") -> 1 | F28: =SUMIFS(Evaluation!$I$2:$I$142,Evaluation!$A$2:$A$142,$B28&"*",Evaluation!$A$2:$A$142,"<>*X*") -> 1
B29: Wat 03 | C29: =SUMIFS(Evaluation!$F$2:$F$142,Evaluation!$A$2:$A$142,$B29&"*",Evaluation!$A$2:$A$142,"<>*X*") -> 1 | D29: =SUMIFS(Evaluation!$G$2:$G$142,Evaluation!$A$2:$A$142,$B29&"*",Evaluation!$A$2:$A$142,"<>*X*") -> 0 | E29: =SUMIFS(Evaluation!$H$2:$H$142,Evaluation!$A$2:$A$142,$B29&"*",Evaluation!$A$2:$A$142,"<>*X*") -> 0 | F29: =SUMIFS(Evaluation!$I$2:$I$142,Evaluation!$A$2:$A$142,$B29&"*",Evaluation!$A$2:$A$142,"<>*X*") -> 2
B30: Wat 04 | C30: =SUMIFS(Evaluation!$F$2:$F$142,Evaluation!$A$2:$A$142,$B30&"*",Evaluation!$A$2:$A$142,"<>*X*") -> 0 | D30: =SUMIFS(Evaluation!$G$2:$G$142,Evaluation!$A$2:$A$142,$B30&"*",Evaluation!$A$2:$A$142,"<>*X*") -> 0 | E30: =SUMIFS(Evaluation!$H$2:$H$142,Evaluation!$A$2:$A$142,$B30&"*",Evaluation!$A$2:$A$142,"<>*X*") -> 0 | F30: =SUMIFS(Evaluation!$I$2:$I$142,Evaluation!$A$2:$A$142,$B30&"*",Evaluation!$A$2:$A$142,"<>*X*") -> 0
B31: Wat 05 | C31: =SUMIFS(Evaluation!$F$2:$F$142,Evaluation!$A$2:$A$142,$B31&"*",Evaluation!$A$2:$A$142,"<>*X*") -> 0 | D31: =SUMIFS(Evaluation!$G$2:$G$142,Evaluation!$A$2:$A$142,$B31&"*",Evaluation!$A$2:$A$142,"<>*X*") -> 0 | E31: =SUMIFS(Evaluation!$H$2:$H$142,Evaluation!$A$2:$A$142,$B31&"*",Evaluation!$A$2:$A$142,"<>*X*") -> 0 | F31: =SUMIFS(Evaluation!$I$2:$I$142,Evaluation!$A$2:$A$142,$B31&"*",Evaluation!$A$2:$A$142,"<>*X*") -> 1
A32: Materials | B32: Mat 01 | C32: =SUMIFS(Evaluation!$F$2:$F$142,Evaluation!$A$2:$A$142,$B32&"*",Evaluation!$A$2:$A$142,"<>*X*") -> 5 | D32: =SUMIFS(Evaluation!$G$2:$G$142,Evaluation!$A$2:$A$142,$B32&"*",Evaluation!$A$2:$A$142,"<>*X*") -> 3 | E32: =SUMIFS(Evaluation!$H$2:$H$142,Evaluation!$A$2:$A$142,$B32&"*",Evaluation!$A$2:$A$142,"<>*X*") -> 3 | F32: =SUMIFS(Evaluation!$I$2:$I$142,Evaluation!$A$2:$A$142,$B32&"*",Evaluation!$A$2:$A$142,"<>*X*") -> 5 | G32: =SUM(C32:C36) -> 12 | H32: =SUM(D32:D36) -> 4 | I32: =SUM(E32:E36) -> 5 | J32: =SUM(F32:F36) -> 7 | K32: =Q8/G32 -> 0.012916667 | L32: =H32*K32 -> 0.051666667 | M32: =I32*K32 -> 0.064583333 | N32: =J32*K32 -> 0.090416667
B33: Mat 02 | C33: =SUMIFS(Evaluation!$F$2:$F$142,Evaluation!$A$2:$A$142,$B33&"*",Evaluation!$A$2:$A$142,"<>*X*") -> 1 | D33: =SUMIFS(Evaluation!$G$2:$G$142,Evaluation!$A$2:$A$142,$B33&"*",Evaluation!$A$2:$A$142,"<>*X*") -> 0 | E33: =SUMIFS(Evaluation!$H$2:$H$142,Evaluation!$A$2:$A$142,$B33&"*",Evaluation!$A$2:$A$142,"<>*X*") -> 0 | F33: =SUMIFS(Evaluation!$I$2:$I$142,Evaluation!$A$2:$A$142,$B33&"*",Evaluation!$A$2:$A$142,"<>*X*") -> 1
B34: Mat 03 | C34: =SUMIFS(Evaluation!$F$2:$F$142,Evaluation!$A$2:$A$142,$B34&"*",Evaluation!$A$2:$A$142,"<>*X*") -> 4 | D34: =SUMIFS(Evaluation!$G$2:$G$142,Evaluation!$A$2:$A$142,$B34&"*",Evaluation!$A$2:$A$142,"<>*X*") -> 0 | E34: =SUMIFS(Evaluation!$H$2:$H$142,Evaluation!$A$2:$A$142,$B34&"*",Evaluation!$A$2:$A$142,"<>*X*") -> 1 | F34: =SUMIFS(Evaluation!$I$2:$I$142,Evaluation!$A$2:$A$142,$B34&"*",Evaluation!$A$2:$A$142,"<>*X*") -> 0
B35: Mat 04 | C35: =SUMIFS(Evaluation!$F$2:$F$142,Evaluation!$A$2:$A$142,$B35&"*",Evaluation!$A$2:$A$142,"<>*X*") -> 1 | D35: =SUMIFS(Evaluation!$G$2:$G$142,Evaluation!$A$2:$A$142,$B35&"*",Evaluation!$A$2:$A$142,"<>*X*") -> 1 | E35: =SUMIFS(Evaluation!$H$2:$H$142,Evaluation!$A$2:$A$142,$B35&"*",Evaluation!$A$2:$A$142,"<>*X*") -> 1 | F35: =SUMIFS(Evaluation!$I$2:$I$142,Evaluation!$A$2:$A$142,$B35&"*",Evaluation!$A$2:$A$142,"<>*X*") -> 1
B36: Mat 05 | C36: =SUMIFS(Evaluation!$F$2:$F$142,Evaluation!$A$2:$A$142,$B36&"*",Evaluation!$A$2:$A$142,"<>*X*") -> 1 | D36: =SUMIFS(Evaluation!$G$2:$G$142,Evaluation!$A$2:$A$142,$B36&"*",Evaluation!$A$2:$A$142,"<>*X*") -> 0 | E36: =SUMIFS(Evaluation!$H$2:$H$142,Evaluation!$A$2:$A$142,$B36&"*",Evaluation!$A$2:$A$142,"<>*X*") -> 0 | F36: =SUMIFS(Evaluation!$I$2:$I$142,Evaluation!$A$2:$A$142,$B36&"*",Evaluation!$A$2:$A$142,"<>*X*") -> 0
A37: Waste | B37: Wst 01 | C37: =SUMIFS(Evaluation!$F$2:$F$142,Evaluation!$A$2:$A$142,$B37&"*",Evaluation!$A$2:$A$142,"<>*X*") -> 4 | D37: =SUMIFS(Evaluation!$G$2:$G$142,Evaluation!$A$2:$A$142,$B37&"*",Evaluation!$A$2:$A$142,"<>*X*") -> 3 | E37: =SUMIFS(Evaluation!$H$2:$H$142,Evaluation!$A$2:$A$142,$B37&"*",Evaluation!$A$2:$A$142,"<>*X*") -> 3 | F37: =SUMIFS(Evaluation!$I$2:$I$142,Evaluation!$A$2:$A$142,$B37&"*",Evaluation!$A$2:$A$142,"<>*X*") -> 3 | G37: =SUM(C37:C42) -> 9 | H37: =SUM(D37:D42) -> 5 | I37: =SUM(E37:E42) -> 5 | J37: =SUM(F37:F42) -> 5 | K37: =Q9/G37 -> 0.0077777778 | L37: =H37*K37 -> 0.038888889 | M37: =I37*K37 -> 0.038888889 | N37: =J37*K37 -> 0.038888889
B38: Wst 02 | C38: =SUMIFS(Evaluation!$F$2:$F$142,Evaluation!$A$2:$A$142,$B38&"*",Evaluation!$A$2:$A$142,"<>*X*") -> 1 | D38: =SUMIFS(Evaluation!$G$2:$G$142,Evaluation!$A$2:$A$142,$B38&"*",Evaluation!$A$2:$A$142,"<>*X*") -> 0 | E38: =SUMIFS(Evaluation!$H$2:$H$142,Evaluation!$A$2:$A$142,$B38&"*",Evaluation!$A$2:$A$142,"<>*X*") -> 0 | F38: =SUMIFS(Evaluation!$I$2:$I$142,Evaluation!$A$2:$A$142,$B38&"*",Evaluation!$A$2:$A$142,"<>*X*") -> 0
B39: Wst 03 | C39: =SUMIFS(Evaluation!$F$2:$F$142,Evaluation!$A$2:$A$142,$B39&"*",Evaluation!$A$2:$A$142,"<>*X*") -> 1 | D39: =SUMIFS(Evaluation!$G$2:$G$142,Evaluation!$A$2:$A$142,$B39&"*",Evaluation!$A$2:$A$142,"<>*X*") -> 1 | E39: =SUMIFS(Evaluation!$H$2:$H$142,Evaluation!$A$2:$A$142,$B39&"*",Evaluation!$A$2:$A$142,"<>*X*") -> 1 | F39: =SUMIFS(Evaluation!$I$2:$I$142,Evaluation!$A$2:$A$142,$B39&"*",Evaluation!$A$2:$A$142,"<>*X*") -> 1
B40: Wst 04 | C40: =SUMIFS(Evaluation!$F$2:$F$142,Evaluation!$A$2:$A$142,$B40&"*",Evaluation!$A$2:$A$142,"<>*X*") -> 0 | D40: =SUMIFS(Evaluation!$G$2:$G$142,Evaluation!$A$2:$A$142,$B40&"*",Evaluation!$A$2:$A$142,"<>*X*") -> 0 | E40: =SUMIFS(Evaluation!$H$2:$H$142,Evaluation!$A$2:$A$142,$B40&"*",Evaluation!$A$2:$A$142,"<>*X*") -> 0 | F40: =SUMIFS(Evaluation!$I$2:$I$142,Evaluation!$A$2:$A$142,$B40&"*",Evaluation!$A$2:$A$142,"<>*X*") -> 0
B41: Wst 05 | C41: =SUMIFS(Evaluation!$F$2:$F$142,Evaluation!$A$2:$A$142,$B41&"*",Evaluation!$A$2:$A$142,"<>*X*") -> 1 | D41: =SUMIFS(Evaluation!$G$2:$G$142,Evaluation!$A$2:$A$142,$B41&"*",Evaluation!$A$2:$A$142,"<>*X*") -> 1 | E41: =SUMIFS(Evaluation!$H$2:$H$142,Evaluation!$A$2:$A$142,$B41&"*",Evaluation!$A$2:$A$142,"<>*X*") -> 1 | F41: =SUMIFS(Evaluation!$I$2:$I$142,Evaluation!$A$2:$A$142,$B41&"*",Evaluation!$A$2:$A$142,"<>*X*") -> 1
B42: Wst 06 | C42: =SUMIFS(Evaluation!$F$2:$F$142,Evaluation!$A$2:$A$142,$B42&"*",Evaluation!$A$2:$A$142,"<>*X*") -> 2 | D42: =SUMIFS(Evaluation!$G$2:$G$142,Evaluation!$A$2:$A$142,$B42&"*",Evaluation!$A$2:$A$142,"<>*X*") -> 0 | E42: =SUMIFS(Evaluation!$H$2:$H$142,Evaluation!$A$2:$A$142,$B42&"*",Evaluation!$A$2:$A$142,"<>*X*") -> 0 | F42: =SUMIFS(Evaluation!$I$2:$I$142,Evaluation!$A$2:$A$142,$B42&"*",Evaluation!$A$2:$A$142,"<>*X*") -> 0
A43: Land Use and ecology | B43: Lue 01 | C43: =SUMIFS(Evaluation!$F$2:$F$142,Evaluation!$A$2:$A$142,$B43&"*",Evaluation!$A$2:$A$142,"<>*X*") -> 3 | D43: =SUMIFS(Evaluation!$G$2:$G$142,Evaluation!$A$2:$A$142,$B43&"*",Evaluation!$A$2:$A$142,"<>*X*") -> 2 | E43: =SUMIFS(Evaluation!$H$2:$H$142,Evaluation!$A$2:$A$142,$B43&"*",Evaluation!$A$2:$A$142,"<>*X*") -> 2 | F43: =SUMIFS(Evaluation!$I$2:$I$142,Evaluation!$A$2:$A$142,$B43&"*",Evaluation!$A$2:$A$142,"<>*X*") -> 2 | G43: =SUM(C43:C47) -> 14 | H43: =SUM(D43:D47) -> 10 | I43: =SUM(E43:E47) -> 11 | J43: =SUM(F43:F47) -> 9 | K43: =Q10/G43 -> 0.0075 | L43: =H43*K43 -> 0.075 | M43: =I43*K43 -> 0.0825 | N43: =J43*K43 -> 0.0675
B44: Lue 02 | C44: =SUMIFS(Evaluation!$F$2:$F$142,Evaluation!$A$2:$A$142,$B44&"*",Evaluation!$A$2:$A$142,"<>*X*") -> 3 | D44: =SUMIFS(Evaluation!$G$2:$G$142,Evaluation!$A$2:$A$142,$B44&"*",Evaluation!$A$2:$A$142,"<>*X*") -> 3 | E44: =SUMIFS(Evaluation!$H$2:$H$142,Evaluation!$A$2:$A$142,$B44&"*",Evaluation!$A$2:$A$142,"<>*X*") -> 3 | F44: =SUMIFS(Evaluation!$I$2:$I$142,Evaluation!$A$2:$A$142,$B44&"*",Evaluation!$A$2:$A$142,"<>*X*") -> 3
B45: Lue 03 | C45: =SUMIFS(Evaluation!$F$2:$F$142,Evaluation!$A$2:$A$142,$B45&"*",Evaluation!$A$2:$A$142,"<>*X*") -> 2 | D45: =SUMIFS(Evaluation!$G$2:$G$142,Evaluation!$A$2:$A$142,$B45&"*",Evaluation!$A$2:$A$142,"<>*X*") -> 2 | E45: =SUMIFS(Evaluation!$H$2:$H$142,Evaluation!$A$2:$A$142,$B45&"*",Evaluation!$A$2:$A$142,"<>*X*") -> 2 | F45: =SUMIFS(Evaluation!$I$2:$I$142,Evaluation!$A$2:$A$142,$B45&"*",Evaluation!$A$2:$A$142,"<>*X*") -> 0
B46: Lue 04 | C46: =SUMIFS(Evaluation!$F$2:$F$142,Evaluation!$A$2:$A$142,$B46&"*",Evaluation!$A$2:$A$142,"<>*X*") -> 4 | D46: =SUMIFS(Evaluation!$G$2:$G$142,Evaluation!$A$2:$A$142,$B46&"*",Evaluation!$A$2:$A$142,"<>*X*") -> 2 | E46: =SUMIFS(Evaluation!$H$2:$H$142,Evaluation!$A$2:$A$142,$B46&"*",Evaluation!$A$2:$A$142,"<>*X*") -> 3 | F46: =SUMIFS(Evaluation!$I$2:$I$142,Evaluation!$A$2:$A$142,$B46&"*",Evaluation!$A$2:$A$142,"<>*X*") -> 2
B47: Lue 05 | C47: =SUMIFS(Evaluation!$F$2:$F$142,Evaluation!$A$2:$A$142,$B47&"*",Evaluation!$A$2:$A$142,"<>*X*") -> 2 | D47: =SUMIFS(Evaluation!$G$2:$G$142,Evaluation!$A$2:$A$142,$B47&"*",Evaluation!$A$2:$A$142,"<>*X*") -> 1 | E47: =SUMIFS(Evaluation!$H$2:$H$142,Evaluation!$A$2:$A$142,$B47&"*",Evaluation!$A$2:$A$142,"<>*X*") -> 1 | F47: =SUMIFS(Evaluation!$I$2:$I$142,Evaluation!$A$2:$A$142,$B47&"*",Evaluation!$A$2:$A$142,"<>*X*") -> 2
A48: Pollution | B48: Pol 01 | C48: =SUMIFS(Evaluation!$F$2:$F$142,Evaluation!$A$2:$A$142,$B48&"*",Evaluation!$A$2:$A$142,"<>*X*") -> 0 | D48: =SUMIFS(Evaluation!$G$2:$G$142,Evaluation!$A$2:$A$142,$B48&"*",Evaluation!$A$2:$A$142,"<>*X*") -> 0 | E48: =SUMIFS(Evaluation!$H$2:$H$142,Evaluation!$A$2:$A$142,$B48&"*",Evaluation!$A$2:$A$142,"<>*X*") -> 0 | F48: =SUMIFS(Evaluation!$I$2:$I$142,Evaluation!$A$2:$A$142,$B48&"*",Evaluation!$A$2:$A$142,"<>*X*") -> 2 | G48: =SUM(C48:C52) -> 6 | H48: =SUM(D48:D52) -> 3 | I48: =SUM(E48:E52) -> 3 | J48: =SUM(F48:F52) -> 10 | K48: =Q11/G48 -> 0.0066666667 | L48: =H48*K48 -> 0.02 | M48: =I48*K48 -> 0.02 | N48: =J48*K48 -> 0.066666667
B49: Pol 02 | C49: =SUMIFS(Evaluation!$F$2:$F$142,Evaluation!$A$2:$A$142,$B49&"*",Evaluation!$A$2:$A$142,"<>*X*") -> 0 | D49: =SUMIFS(Evaluation!$G$2:$G$142,Evaluation!$A$2:$A$142,$B49&"*",Evaluation!$A$2:$A$142,"<>*X*") -> 0 | E49: =SUMIFS(Evaluation!$H$2:$H$142,Evaluation!$A$2:$A$142,$B49&"*",Evaluation!$A$2:$A$142,"<>*X*") -> 0 | F49: =SUMIFS(Evaluation!$I$2:$I$142,Evaluation!$A$2:$A$142,$B49&"*",Evaluation!$A$2:$A$142,"<>*X*") -> 3
B50: Pol 03 | C50: =SUMIFS(Evaluation!$F$2:$F$142,Evaluation!$A$2:$A$142,$B50&"*",Evaluation!$A$2:$A$142,"<>*X*") -> 5 | D50: =SUMIFS(Evaluation!$G$2:$G$142,Evaluation!$A$2:$A$142,$B50&"*",Evaluation!$A$2:$A$142,"<>*X*") -> 2 | E50: =SUMIFS(Evaluation!$H$2:$H$142,Evaluation!$A$2:$A$142,$B50&"*",Evaluation!$A$2:$A$142,"<>*X*") -> 2 | F50: =SUMIFS(Evaluation!$I$2:$I$142,Evaluation!$A$2:$A$142,$B50&"*",Evaluation!$A$2:$A$142,"<>*X*") -> 3
B51: Pol 04 | C51: =SUMIFS(Evaluation!$F$2:$F$142,Evaluation!$A$2:$A$142,$B51&"*",Evaluation!$A$2:$A$142,"<>*X*") -> 1 | D51: =SUMIFS(Evaluation!$G$2:$G$142,Evaluation!$A$2:$A$142,$B51&"*",Evaluation!$A$2:$A$142,"<>*X*") -> 1 | E51: =SUMIFS(Evaluation!$H$2:$H$142,Evaluation!$A$2:$A$142,$B51&"*",Evaluation!$A$2:$A$142,"<>*X*") -> 1 | F51: =SUMIFS(Evaluation!$I$2:$I$142,Evaluation!$A$2:$A$142,$B51&"*",Evaluation!$A$2:$A$142,"<>*X*") -> 1
B52: Pol 05 | C52: =SUMIFS(Evaluation!$F$2:$F$142,Evaluation!$A$2:$A$142,$B52&"*",Evaluation!$A$2:$A$142,"<>*X*") -> 0 | D52: =SUMIFS(Evaluation!$G$2:$G$142,Evaluation!$A$2:$A$142,$B52&"*",Evaluation!$A$2:$A$142,"<>*X*") -> 0 | E52: =SUMIFS(Evaluation!$H$2:$H$142,Evaluation!$A$2:$A$142,$B52&"*",Evaluation!$A$2:$A$142,"<>*X*") -> 0 | F52: =SUMIFS(Evaluation!$I$2:$I$142,Evaluation!$A$2:$A$142,$B52&"*",Evaluation!$A$2:$A$142,"<>*X*") -> 1
A53: Innovation | B53: Man 03X | C53: =SUMIFS(Evaluation!$F$2:$F$142,Evaluation!$A$2:$A$142,$B53&"*") -> 1 | D53: =SUMIFS(Evaluation!$G$2:$G$142,Evaluation!$A$2:$A$142,$B53&"*") -> 0 | E53: =SUMIFS(Evaluation!$H$2:$H$142,Evaluation!$A$2:$A$142,$B53&"*") -> 0 | F53: =SUMIFS(Evaluation!$I$2:$I$142,Evaluation!$A$2:$A$142,$B53&"*") -> 1 | G53: =SUM(C53:C69) -> 10 | H53: =SUM(D53:D69) -> 1 | I53: =SUM(E53:E69) -> 1 | J53: =SUM(F53:F69) -> 14 | K53: =0.01 -> 0.01 | L53: =H53*K53 -> 0.01 | M53: =I53*K53 -> 0.01 | N53: =J53*K53 -> 0.14
B54: Man 05X | C54: =SUMIFS(Evaluation!$F$2:$F$142,Evaluation!$A$2:$A$142,$B54&"*") -> 0 | D54: =SUMIFS(Evaluation!$G$2:$G$142,Evaluation!$A$2:$A$142,$B54&"*") -> 0 | E54: =SUMIFS(Evaluation!$H$2:$H$142,Evaluation!$A$2:$A$142,$B54&"*") -> 0 | F54: =SUMIFS(Evaluation!$I$2:$I$142,Evaluation!$A$2:$A$142,$B54&"*") -> 1
B55: Hea 01X | C55: =SUMIFS(Evaluation!$F$2:$F$142,Evaluation!$A$2:$A$142,$B55&"*") -> 1 | D55: =SUMIFS(Evaluation!$G$2:$G$142,Evaluation!$A$2:$A$142,$B55&"*") -> 0 | E55: =SUMIFS(Evaluation!$H$2:$H$142,Evaluation!$A$2:$A$142,$B55&"*") -> 0 | F55: =SUMIFS(Evaluation!$I$2:$I$142,Evaluation!$A$2:$A$142,$B55&"*") -> 1
B56: Hea 02X | C56: =SUMIFS(Evaluation!$F$2:$F$142,Evaluation!$A$2:$A$142,$B56&"*") -> 0 | D56: =SUMIFS(Evaluation!$G$2:$G$142,Evaluation!$A$2:$A$142,$B56&"*") -> 0 | E56: =SUMIFS(Evaluation!$H$2:$H$142,Evaluation!$A$2:$A$142,$B56&"*") -> 0 | F56: =SUMIFS(Evaluation!$I$2:$I$142,Evaluation!$A$2:$A$142,$B56&"*") -> 0
B57: Hea 04X | C57: =SUMIFS(Evaluation!$F$2:$F$142,Evaluation!$A$2:$A$142,$B57&"*") -> 0 | D57: =SUMIFS(Evaluation!$G$2:$G$142,Evaluation!$A$2:$A$142,$B57&"*") -> 0 | E57: =SUMIFS(Evaluation!$H$2:$H$142,Evaluation!$A$2:$A$142,$B57&"*") -> 0 | F57: =SUMIFS(Evaluation!$I$2:$I$142,Evaluation!$A$2:$A$142,$B57&"*") -> 1
B58: Hea 07X | C58: =SUMIFS(Evaluation!$F$2:$F$142,Evaluation!$A$2:$A$142,$B58&"*") -> 1 | D58: =SUMIFS(Evaluation!$G$2:$G$142,Evaluation!$A$2:$A$142,$B58&"*") -> 0 | E58: =SUMIFS(Evaluation!$H$2:$H$142,Evaluation!$A$2:$A$142,$B58&"*") -> 0 | F58: =SUMIFS(Evaluation!$I$2:$I$142,Evaluation!$A$2:$A$142,$B58&"*") -> 1
B59: Ene 01X | C59: =SUMIFS(Evaluation!$F$2:$F$142,Evaluation!$A$2:$A$142,$B59&"*") -> 0 | D59: =SUMIFS(Evaluation!$G$2:$G$142,Evaluation!$A$2:$A$142,$B59&"*") -> 0 | E59: =SUMIFS(Evaluation!$H$2:$H$142,Evaluation!$A$2:$A$142,$B59&"*") -> 0 | F59: =SUMIFS(Evaluation!$I$2:$I$142,Evaluation!$A$2:$A$142,$B59&"*") -> 0
B60: Ene 02X | C60: =SUMIFS(Evaluation!$F$2:$F$142,Evaluation!$A$2:$A$142,$B60&"*") -> 0 | D60: =SUMIFS(Evaluation!$G$2:$G$142,Evaluation!$A$2:$A$142,$B60&"*") -> 0 | E60: =SUMIFS(Evaluation!$H$2:$H$142,Evaluation!$A$2:$A$142,$B60&"*") -> 0 | F60: =SUMIFS(Evaluation!$I$2:$I$142,Evaluation!$A$2:$A$142,$B60&"*") -> 4
B61: Wat 01X | C61: =SUMIFS(Evaluation!$F$2:$F$142,Evaluation!$A$2:$A$142,$B61&"*") -> 0 | D61: =SUMIFS(Evaluation!$G$2:$G$142,Evaluation!$A$2:$A$142,$B61&"*") -> 0 | E61: =SUMIFS(Evaluation!$H$2:$H$142,Evaluation!$A$2:$A$142,$B61&"*") -> 0 | F61: =SUMIFS(Evaluation!$I$2:$I$142,Evaluation!$A$2:$A$142,$B61&"*") -> 0
B62: Wat 05X | C62: =SUMIFS(Evaluation!$F$2:$F$142,Evaluation!$A$2:$A$142,$B62&"*") -> 0 | D62: =SUMIFS(Evaluation!$G$2:$G$142,Evaluation!$A$2:$A$142,$B62&"*") -> 0 | E62: =SUMIFS(Evaluation!$H$2:$H$142,Evaluation!$A$2:$A$142,$B62&"*") -> 0 | F62: =SUMIFS(Evaluation!$I$2:$I$142,Evaluation!$A$2:$A$142,$B62&"*") -> 1
B63: Mat 01X | C63: =SUMIFS(Evaluation!$F$2:$F$142,Evaluation!$A$2:$A$142,$B63&"*") -> 2 | D63: =SUMIFS(Evaluation!$G$2:$G$142,Evaluation!$A$2:$A$142,$B63&"*") -> 0 | E63: =SUMIFS(Evaluation!$H$2:$H$142,Evaluation!$A$2:$A$142,$B63&"*") -> 0 | F63: =SUMIFS(Evaluation!$I$2:$I$142,Evaluation!$A$2:$A$142,$B63&"*") -> 2
B64: Mat 03X | C64: =SUMIFS(Evaluation!$F$2:$F$142,Evaluation!$A$2:$A$142,$B64&"*") -> 1 | D64: =SUMIFS(Evaluation!$G$2:$G$142,Evaluation!$A$2:$A$142,$B64&"*") -> 0 | E64: =SUMIFS(Evaluation!$H$2:$H$142,Evaluation!$A$2:$A$142,$B64&"*") -> 0 | F64: =SUMIFS(Evaluation!$I$2:$I$142,Evaluation!$A$2:$A$142,$B64&"*") -> 0
B65: Wst 01X | C65: =SUMIFS(Evaluation!$F$2:$F$142,Evaluation!$A$2:$A$142,$B65&"*") -> 1 | D65: =SUMIFS(Evaluation!$G$2:$G$142,Evaluation!$A$2:$A$142,$B65&"*") -> 1 | E65: =SUMIFS(Evaluation!$H$2:$H$142,Evaluation!$A$2:$A$142,$B65&"*") -> 1 | F65: =SUMIFS(Evaluation!$I$2:$I$142,Evaluation!$A$2:$A$142,$B65&"*") -> 0
... B69: Lue 04X | C69: =SUMIFS(Evaluation!$F$2:$F$142,Evaluation!$A$2:$A$142,$B69&"*") -> 1 | D69: =SUMIFS(Evaluation!$G$2:$G$142,Evaluation!$A$2:$A$142,$B69&"*") -> 0 | E69: =SUMIFS(Evaluation!$H$2:$H$142,Evaluation!$A$2:$A$142,$B69&"*") -> 0 | F69: =SUMIFS(Evaluation!$I$2:$I$142,Evaluation!$A$2:$A$142,$B69&"*") -> 1

Sheet Points à prendre
C3: 0.289 | F3: Crédit | G3: Action | H3: Critère | I3: Estimation du nombre de points atteignables | J3: Nombre de points atteignables | K3: Coût H.T. (estimation) | L3: Commentaire | M3: Responsable | N3: mission sous traitée
C4: 0.0106 | F4: Man 01 | G4: Consultation des tierces parties | H4: 5-8 | I4: 1 | J4: =I4*#REF! -> #REF! | K4: =585*9 -> 5265 | L4: Consulter l'ambassade d'Espagne, et les copropriétés adjacentes sur la base d'un descriptif du projet. Prendre en compte leurs retours dans la mesure du possible. | M4: SPACE | N4: Oui
C5: 0.0053 | F5: Hea 02 | G5: Mesure de la qualité de l'air intérieur post-construction | H5: 11-17 | I5: 1 | J5: =I5*#REF! -> #REF! | K5: 0 | L5: Mesurer la qualité de l'air post-construction. Obtenir des niveaux de Formaldéhyde ≤ 100 µg/m3 et de COVT ≤ 300 µg/m3. | M5: - | N5: -
C6: 0.0159 | F6: Hea 04 | G6: Adaptabilité - pour une projection de scénario de changement climatique | H6: 5-8 | I6: 1 | J6: =I6*#REF! -> #REF! | K6: =585*2 -> 1170 | L6: Prouver, via simulation, l'obtention des conditions de confort thermique en prenant pour hypothèse le scénario de réchauffement climatique A1B du GIEC à horizon +15 ans | M6: SPACE O | N6: Non
C7: 0.0122 | F7: Ene 04 | G7: Analyse de la conception passive | H7: 1-3 | I7: 1 | J7: =I7*#REF! -> #REF! | K7: =5*585 -> 2925 | L7: Optimiser l'enveloppe du bâtiment à partir des enseignements de la simulation thermique dynamique. (réalisation de la simulation en phase amont) | M7: SPACE O | N7: Non
C8: 0.0122 | F8: Mat 03 | G8: Approvisionnement responsable en matériaux de construction | H8: 1-5 | I8: 1 | J8: =I8*#REF! -> #REF! | K8: =12*585 -> 7020 | L8: Rédiger un plan d'approvisionnement responsable, qui impose à l'entreprise d'utiliser, pour les produits représentant les plus gros volumes, des produits provenant d'usines certifiées (type ISO 14001 / FSC / PEFC,..) | M8: SPACE O | N8: Non
C9: 0.0244 | F9: Wst 01 | G9: Réduction des déchets de construction | H9: 1-8 | I9: 2 | J9: =I9*#REF! -> #REF! | K9: 0 | L9: Mener un audit préalable à la démolition pour identifier les éventuels potentiels de réutilisation et les différentes typologies de déchets. | M9: - | N9: -
C10: 0.0122 | F10: Wst 06 | G10: Adaptabilité fonctionnelle | H10: 1-2 | I10: 1 | J10: =I10*#REF! -> #REF! | L10: Mettre en place une stratégie d'adaptabilité du projet. (envisager un remplacement de la façade et des équipements techniques de production)
C11: 0.01 | F11: Hea 06 | G11: Bâtiment accessible | H11: 12-14 | I11: 1 | J11: =I11*#REF! -> #REF! | L11: Bâtiment inclusif dans son ensemble. Plus particulièrement pour: les personnes à mobilité réduite, toutes les tranches d'âge, origine, genre, forme physique, les personnes accompagnées d'enfants. Voir checklist A3
C12: 0.0061 | F12: Hea 09 | G12: Qualité de l'eau | H12: 1-4 | I12: 1 | J12: =I12*#REF! -> #REF! | K12: 2340 | L12: Conception minimisant le risque de contamination microbienne dans le système de distribution d'eau. Mise à disposition d'eau potable saine dans tous les espaces occupés de façon permanente | M12: SPACE O | N12: Non
C13: 0.01 | F13: Ene 01X | G13: Niveau exemplaire | H13: 7-12 | I13: 1 | J13: =I13*#REF! -> #REF! | K13: =7*585 -> 4095 | L13: Jusqu'à 4 points : bilan de zéro émissions de CO₂ 5 points : bilan positif énergie consommée, énergie produite | M13: SPACE O | N13: Non
C14: 0.0105 | F14: Ene 06 | G14: Systèmes de transport Consommation d'énergie | H14: 1 | I14: 1 | J14: =I14*#REF! -> #REF! | K14: =3*585 -> 1755 | L14: Pour les systèmes de transport neufs, une analyse de la demande de transport a été effectuée pour déterminer le nombre et la taille optimum des ascenseurs. La consommation énergétique a été estimée conformément à la norme ISO/DIS 25745, pour l’un des éléments suivants : - Au moins deux types de systèmes (pour chacun des types de transport prévus) ; OU - Une combinaison de systèmes (par ex. pour les ascenseurs ou monte-charges, hydraulique, par traction, sans local machinerie (MRL)) ; OU - Une stratégie de systèmes « adaptée à l’utilisation ». Le système de transport à la consommation énergétique la plus basse est retenu. L’emploi d’un système d’entraînement régénératif est à considérer si l'économie est supérieure à sa consommation en veille. | M14: SPACE | N14: Non
C15: 0.006 | F15: Ene 06 | G15: Systèmes de transport Caractéristiques d'économie en énergie | H15: 2-6 | I15: 2 | J15: =I15*#REF! -> #REF! | K15: =10*585 -> 5850 | L15: Pour chaque ascenseur neuf, les 3 caractéristiques éco énergétiques suivantes sont prévues (2 des 3 pour les machines existantes) : - Au cours des périodes creuses, l’ascenseur se met en état de veille, par ex. la partie des commandes de l’ascenseur alimentée à l’électricité et d’autres équipements de fonctionnement, tels que l’éclairage de la cabine, l’affichage lumineux pour les usagers et la ventilation, s’arrêtent lorsque l’ascenseur n’a pas été utilisé pendant une durée donnée. - L’ascenseur dispose d’un éclairage et d’un affichage lumineux d’une efficacité lumineuse moyenne supérieure à 55 lumens par Watt. - L’ascenseur dispose d’un système de contrôle à vitesse variable, d’un variateur de tension et d’un variateur de fréquence pour le moteur. Lorsqu’il est prouvé que l’emploi d’entraînements régénératifs pourra économiser de l’énergie, ceux-ci sont prévus. | M15: SPACE | N15: Oui
C16: 0.4033 | F16: Pol 02 | G16: Emissions de NOx | H16: 1-2 | I16: 1 | J16: =I16*#REF! -> #REF! | K16: =10*585 -> 5850 | L16: Les équipements installés pour répondre à la demande du bâtiment en chauffage et en eau chaude présentent, dans des conditions normales de fonctionnement, des niveaux d’émission de NOx secs (mesurés avec 0 % d’excès d’O2) comme suit : ≤ 56 mg/kWh pour 1 crédit ≤ 40 mg/kWh pour 2 crédits | M16: SPACE | N16: Oui
C17: 0.0095 | F17: Pol 03 | G17: Ruissellement de surface | H17: 4-16 | I17: 1 | J17: =I17*#REF! -> #REF! | K17: =585*47 -> 27495 | L17: Il n’y a pas d’augmentation des surfaces imperméables due au projet, et un contrat de maintenance est prévu pour les systèmes de gestion des eaux pluviales. La réglementation est respectée en prenant en compte un scénario de pluie intégrant le changement climatique. | M17: SPACE | N17: oui
C18: 0.0095 | I18: =SUBTOTAL(109,Tableau5[Estimation du nombre de points atteignables]) -> 16 | J18: =SUBTOTAL(109,Tableau5[Nombre de points atteignables]) -> #REF!
C19: 0.0095
C20: 0.021
C21: 0.012
C22: 29 600 €HT
